[
    {
        "solicitante": "ROMES ROSA SILVA",
        "frota": "5760",
        "modelo": "PULVERIZADOR 4000 SMART DUPLO",
        "os": "118357",
        "data_entrada": "16/09/2025",
        "previsao_saida": "---",
        "prestador": "nan",
        "servico": "Verificar sistema eletrico da abertura do pistão, verificar bobina queimada - (Fazenda São Pedro)",
        "liberado_por": "Arthur"
    },
    {
        "solicitante": "EDER JOSE FERNANDES DE ALMEIDA",
        "frota": "10222",
        "modelo": "TRATOR JOHN DEERE 5080E",
        "os": "118356",
        "data_entrada": "16/09/2025",
        "previsao_saida": "---",
        "prestador": "nan",
        "servico": "Vazamento de óleo nos tuchos do comando hidráulico (Fazenda Terra Branca)",
        "liberado_por": "Arthur"
    },
    {
        "solicitante": "IZAIAS FRANCISCO DA SILVA",
        "frota": "197",
        "modelo": "TRATOR JOHN DEERE 5080E",
        "os": "118351",
        "data_entrada": "16/09/2025",
        "previsao_saida": "---",
        "prestador": "PEDRO PEREIRA MONTESSANI EIRELI - ME",
        "servico": "Verificar trator sem partida, motor de partida estalando - (Fazenda Alvorada)",
        "liberado_por": "Arthur"
    },
    {
        "solicitante": "EDER JOSE FERNANDES DE ALMEIDA",
        "frota": "341",
        "modelo": "TRATOR NEW HOLANDTL5.80",
        "os": "118342",
        "data_entrada": "16/09/2025",
        "previsao_saida": "---",
        "prestador": "EQUAGRIL EQUIPAMENTOS AGRICOLAS LTDA",
        "servico": "Verificar vazamento de óleo de hidráulico, aparentemente no retentor da caixa seca - (Fazenda Terra Branca)",
        "liberado_por": "Arthur"
    },
    {
        "solicitante": "PAULO EDSON ABREU VILELA JUNIOR",
        "frota": "165",
        "modelo": "TRATOR JOHN DEERE 6415 4X4",
        "os": "118321",
        "data_entrada": "15/09/2025",
        "previsao_saida": "---",
        "prestador": "nan",
        "servico": "Verificar trator aquecendo - (Fazenda SP)",
        "liberado_por": "Arthur"
    },
    {
        "solicitante": "ROMES ROSA SILVA",
        "frota": "195",
        "modelo": "TRATOR JOHN DEERE 5080E",
        "os": "118311",
        "data_entrada": "15/09/2025",
        "previsao_saida": "---",
        "prestador": "PEDRO PEREIRA MONTESSANI EIRELI - ME",
        "servico": "Verificar cibiés não ascendem - (Fazenda São Pedro)",
        "liberado_por": "Arthur"
    },
    {
        "solicitante": "EDER JOSE FERNANDES DE ALMEIDA",
        "frota": "224",
        "modelo": "TRATOR JOHN DEERE 5080E",
        "os": "118303",
        "data_entrada": "15/09/2025",
        "previsao_saida": "---",
        "prestador": "nan",
        "servico": "Verificar trator aquecendo e perdendo força - (Fazenda Terra Branca)",
        "liberado_por": "Arthur"
    },
    {
        "solicitante": "RENNAN ARCANJO CREPALDI",
        "frota": "303",
        "modelo": "TRATOR JOHN DEERE 5080E",
        "os": "118299",
        "data_entrada": "15/09/2025",
        "previsao_saida": "---",
        "prestador": "nan",
        "servico": "Cano e mangueira da bomba injetora furado - (Fazenda NSA)",
        "liberado_por": "Arthur"
    },
    {
        "solicitante": "ALTIERES SOARES FERREIRA",
        "frota": "97",
        "modelo": "TRATOR JOHN DEERE 5065 4X4",
        "os": "118298",
        "data_entrada": "15/09/2025",
        "previsao_saida": "---",
        "prestador": "nan",
        "servico": "Motor apresentando vazamento de óleo pela vareta de nível, bomba injetora e suspiro, acompanhado de emissão anormal de fumaça em excesso. Indícios de pressão elevada no cárter ou desgaste interno de componentes. - (Fazenda Pedra Verde)",
        "liberado_por": "Arthur"
    },
    {
        "solicitante": "CASSIO ANTONIO MARTINS NASCIMENTO",
        "frota": "5660",
        "modelo": "PULVERIZADOR 4000 LT JACTO",
        "os": "118291",
        "data_entrada": "15/09/2025",
        "previsao_saida": "---",
        "prestador": "nan",
        "servico": "Verificar caixa de comando para abertura dos  ramais não funciona - (Fazenda São Severino)",
        "liberado_por": "Arthur"
    },
    {
        "solicitante": "JOSIMAR BADIAS DE JESUS",
        "frota": "276",
        "modelo": "TRATOR JOHN DEERE 5080E",
        "os": "118288",
        "data_entrada": "15/09/2025",
        "previsao_saida": "---",
        "prestador": "nan",
        "servico": "Verificar lâmpada do farol \"estourando\" - (Fazenda São Pedro)",
        "liberado_por": "Arthur"
    },
    {
        "solicitante": "NATALINO ANTONIO JUSTINO",
        "frota": "247",
        "modelo": "TRATOR JOHN DEERE 5080EN",
        "os": "118247",
        "data_entrada": "13/09/2025",
        "previsao_saida": "---",
        "prestador": "ANDERSON DIEGO BICUDO 08122062903",
        "servico": "Terminal da barra de direção L/D com parafuso expando - (Fazenda Alvorada)",
        "liberado_por": "Arthur"
    },
    {
        "solicitante": "ROMES ROSA SILVA",
        "frota": "260",
        "modelo": "TRATOR JOHN DEERE 5080E",
        "os": "118244",
        "data_entrada": "13/09/2025",
        "previsao_saida": "---",
        "prestador": "PEDRO PEREIRA MONTESSANI EIRELI - ME",
        "servico": "Trocar terminais com porta fusível do tanque de pulverização (Alma)",
        "liberado_por": "Arthur"
    },
    {
        "solicitante": "PAULO EDSON ABREU VILELA JUNIOR",
        "frota": "165",
        "modelo": "TRATOR JOHN DEERE 6415 4X4",
        "os": "118233",
        "data_entrada": "12/09/2025",
        "previsao_saida": "---",
        "prestador": "INJECOES DIESEL NOROESTE LTDA.",
        "servico": "Trator afogando e perdendo rotação (Fazenda SP)",
        "liberado_por": "Arthur"
    },
    {
        "solicitante": "JOAO PAULO DE OLIVEIRA PORTEIRO",
        "frota": "10220",
        "modelo": "TRATOR JOHN DEERE 5080E",
        "os": "118223",
        "data_entrada": "12/09/2025",
        "previsao_saida": "---",
        "prestador": "COCAMAR MAQUINAS AGRICOLAS LTDA.",
        "servico": "Verificar 3° marcha encavalada e freio estacionário escapando - (Fazenda Casa Branca)",
        "liberado_por": "Arthur"
    },
    {
        "solicitante": "IZAIAS FRANCISCO DA SILVA",
        "frota": "191",
        "modelo": "TRATOR NEW HOLAND TL 5.80",
        "os": "118180",
        "data_entrada": "12/09/2025",
        "previsao_saida": "---",
        "prestador": "INJECOES DIESEL NOROESTE LTDA.",
        "servico": "Verificar trator sem partida - (Fazenda São Severino)|Parado|",
        "liberado_por": "Arthur"
    },
    {
        "solicitante": "JOSIMAR BADIAS DE JESUS",
        "frota": "195",
        "modelo": "TRATOR JOHN DEERE 5080E",
        "os": "118177",
        "data_entrada": "12/09/2025",
        "previsao_saida": "---",
        "prestador": "PEDRO PEREIRA MONTESSANI EIRELI - ME",
        "servico": "Verificar cibiés não ascendem - (Fazenda São Pedro)",
        "liberado_por": "Arthur"
    },
    {
        "solicitante": "ELISMAR SIQUEIRA DA SILVA JUNIOR",
        "frota": "106",
        "modelo": "TRATOR JOHN DEERE 5078 E 4X4",
        "os": "118168",
        "data_entrada": "12/09/2025",
        "previsao_saida": "---",
        "prestador": "JOSE RENATO LEMES MARINHO 06173795990",
        "servico": "Remover teto quebrado para recuperar - (Fazenda Nova Manhã)",
        "liberado_por": "Arthur"
    },
    {
        "solicitante": "JOSIMAR BADIAS DE JESUS",
        "frota": "264",
        "modelo": "TRATOR JOHN DEERE 5080E",
        "os": "118165",
        "data_entrada": "12/09/2025",
        "previsao_saida": "---",
        "prestador": "nan",
        "servico": "Vazamento de óleo de motor na junta do cárter - (Fazenda São Pedro)",
        "liberado_por": "Arthur"
    },
    {
        "solicitante": "MURILO J ONCK LEMES DA SILVA",
        "frota": "102",
        "modelo": "TRATOR JOHN DEERE 5065 4X4",
        "os": "118160",
        "data_entrada": "12/09/2025",
        "previsao_saida": "---",
        "prestador": "nan",
        "servico": "Verificar vazamento no MAP e verificar bomba hidráulica - (Fazenda Bela Manhã)",
        "liberado_por": "Arthur"
    },
    {
        "solicitante": "IZAIAS FRANCISCO DA SILVA",
        "frota": "10221",
        "modelo": "TRATOR JOHN DEERE 5080E",
        "os": "118158",
        "data_entrada": "12/09/2025",
        "previsao_saida": "---",
        "prestador": "PEDRO PEREIRA MONTESSANI EIRELI - ME",
        "servico": "Verificar curto na caixa de fusíveis - (Fazenda Minuano)|Parado|",
        "liberado_por": "Arthur"
    },
    {
        "solicitante": "RENNAN ARCANJO CREPALDI",
        "frota": "303",
        "modelo": "TRATOR JOHN DEERE 5080E",
        "os": "118147",
        "data_entrada": "11/09/2025",
        "previsao_saida": "---",
        "prestador": "nan",
        "servico": "Valvular do tanque de combustível perdida  e fechadura da porta travada- (Fazenda NSA)|Parado|",
        "liberado_por": "Arthur"
    },
    {
        "solicitante": "NATALINO ANTONIO JUSTINO",
        "frota": "121",
        "modelo": "TRATOR MASSEY FERGUSON 4275/4",
        "os": "118135",
        "data_entrada": "11/09/2025",
        "previsao_saida": "---",
        "prestador": "MASON EQUIPAMENTOS AGRICOLAS LTDA (UMUA)",
        "servico": "Quebra do cabo do acelerador de mão - (Fazenda Alvorada)",
        "liberado_por": "Arthur"
    },
    {
        "solicitante": "ADRIANO CLAUDIO FIRMINO",
        "frota": "106",
        "modelo": "TRATOR JOHN DEERE 5078 E 4X4",
        "os": "118125",
        "data_entrada": "11/09/2025",
        "previsao_saida": "---",
        "prestador": "SOLO VERDE - MANUTENÇÃO AGRÍCOLA",
        "servico": "Verificar TDP bem lenta (Fazenda Nova Manhã)",
        "liberado_por": "Arthur"
    },
    {
        "solicitante": "MARCIO APARECIDO CRUZ",
        "frota": "118",
        "modelo": "TRATOR JOHN DEERE 5078 E 4X4",
        "os": "118113",
        "data_entrada": "11/09/2025",
        "previsao_saida": "---",
        "prestador": "SOLO VERDE - MANUTENÇÃO AGRÍCOLA",
        "servico": "Verificar volante não segura as travas e vazamento de óleo hidráulicos nos tuchos do comando - (Fazenda Minuano)",
        "liberado_por": "Arthur"
    },
    {
        "solicitante": "ROMES ROSA SILVA",
        "frota": "10226",
        "modelo": "TRATOR JOHN DEERE 5080E",
        "os": "118109",
        "data_entrada": "11/09/2025",
        "previsao_saida": "---",
        "prestador": "PEDRO PEREIRA MONTESSANI EIRELI - ME",
        "servico": "Verificar luzes do alerta não funciona - (Fazenda São Pedro)",
        "liberado_por": "Arthur"
    },
    {
        "solicitante": "PAULO EDSON ABREU VILELA JUNIOR",
        "frota": "270",
        "modelo": "TRATOR JOHN DEERE 5080E",
        "os": "118083",
        "data_entrada": "10/09/2025",
        "previsao_saida": "---",
        "prestador": "JOSE RENATO LEMES MARINHO 06173795990",
        "servico": "Soldar escapamento (Fazenda São Paulo)",
        "liberado_por": "Arthur"
    },
    {
        "solicitante": "ALTIERES SOARES FERREIRA",
        "frota": "76",
        "modelo": "TRATOR JOHN DEERE 5403 4X4",
        "os": "118080",
        "data_entrada": "10/09/2025",
        "previsao_saida": "---",
        "prestador": "nan",
        "servico": "Vazamento  no retentor da planetária L/E - (Fazenda Pedra Verde)",
        "liberado_por": "Arthur"
    },
    {
        "solicitante": "PAULO EDSON ABREU VILELA JUNIOR",
        "frota": "10219",
        "modelo": "TRATOR JOHN DEERE 5080E",
        "os": "118079",
        "data_entrada": "10/09/2025",
        "previsao_saida": "---",
        "prestador": "nan",
        "servico": "Verificar trator sem tração - (Fazenda São Paulo)",
        "liberado_por": "Arthur"
    },
    {
        "solicitante": "ROMES ROSA SILVA",
        "frota": "117",
        "modelo": "TRATOR JOHN DEERE 5078 E 4X4",
        "os": "118062",
        "data_entrada": "10/09/2025",
        "previsao_saida": "---",
        "prestador": "OMC MANUTENCAO DE MAQUINAS AGRICOLAS LT",
        "servico": "Retirar vazamento da junta do carter (Fazenda São Pedro)",
        "liberado_por": "Arthur"
    },
    {
        "solicitante": "ELISMAR SIQUEIRA DA SILVA JUNIOR",
        "frota": "130",
        "modelo": "TRATOR JOHN DEERE 5075 E 4X4",
        "os": "118059",
        "data_entrada": "10/09/2025",
        "previsao_saida": "---",
        "prestador": "SOLO VERDE - MANUTENÇÃO AGRÍCOLA",
        "servico": "Retentor dianteiro estourado (Fazenda Nova Manhã)",
        "liberado_por": "Arthur"
    },
    {
        "solicitante": "CASSIO ANTONIO MARTINS NASCIMENTO",
        "frota": "64",
        "modelo": "TRATOR JOHN DEERE 5603 4X4",
        "os": "118032",
        "data_entrada": "10/09/2025",
        "previsao_saida": "---",
        "prestador": "JOSE RENATO LEMES MARINHO 06173795990",
        "servico": "Fazer solda em trinca na tubagem do escapamento - (Fazenda São Severino)",
        "liberado_por": "Arthur"
    },
    {
        "solicitante": "ROMES ROSA SILVA",
        "frota": "252",
        "modelo": "TRATOR JOHN DEERE 5080E",
        "os": "118011",
        "data_entrada": "09/09/2025",
        "previsao_saida": "---",
        "prestador": "PEDRO PEREIRA MONTESSANI EIRELI - ME",
        "servico": "Substituir sensor da TDP  - (Fazenda São Pedro)",
        "liberado_por": "Arthur"
    },
    {
        "solicitante": "MURILO J ONCK LEMES DA SILVA",
        "frota": "218",
        "modelo": "TRATOR JOHN DEERE 5080E",
        "os": "117952",
        "data_entrada": "09/09/2025",
        "previsao_saida": "---",
        "prestador": "INJECOES DIESEL NOROESTE LTDA.",
        "servico": "Vazamento de óleo diesel no eixo da bomba injetora - (Fazenda Bela Manhã)",
        "liberado_por": "Arthur"
    },
    {
        "solicitante": "ALTIERES SOARES FERREIRA",
        "frota": "69",
        "modelo": "TRATOR JOHN DEERE 5403 4X4",
        "os": "117950",
        "data_entrada": "09/09/2025",
        "previsao_saida": "---",
        "prestador": "SOLO VERDE - MANUTENÇÃO AGRÍCOLA",
        "servico": "Sacar parafuso quebrado na alavanca da TDP - (Fazenda Pedra Verde)",
        "liberado_por": "Arthur"
    },
    {
        "solicitante": "GEOVANE LIBERO DA SILVA",
        "frota": "135",
        "modelo": "TRATOR NEW HOLLAND TT3880F 4X4",
        "os": "117930",
        "data_entrada": "09/09/2025",
        "previsao_saida": "---",
        "prestador": "PEDRO PEREIRA MONTESSANI EIRELI - ME",
        "servico": "Verificar relógio horimetro não funciona - (Fazenda Biscui)",
        "liberado_por": "Arthur"
    },
    {
        "solicitante": "ARTHUR SOUSA OLIVEIRA",
        "frota": "198",
        "modelo": "TRATOR JOHN DEERE 5080E",
        "os": "117880",
        "data_entrada": "08/09/2025",
        "previsao_saida": "---",
        "prestador": "ANDERSON DIEGO BICUDO 08122062903",
        "servico": "Verificar trator travando o parker - (Fazenda Estrela)",
        "liberado_por": "Arthur"
    },
    {
        "solicitante": "CASSIO ANTONIO MARTINS NASCIMENTO",
        "frota": "5599",
        "modelo": "PREMIX PRIME 2T 2000",
        "os": "117865",
        "data_entrada": "08/09/2025",
        "previsao_saida": "---",
        "prestador": "PEDRO PEREIRA MONTESSANI EIRELI - ME",
        "servico": "Revisar chicote eletrico do pré-mix - (Fazenda São Severino)",
        "liberado_por": "Arthur"
    },
    {
        "solicitante": "PAULO EDSON ABREU VILELA JUNIOR",
        "frota": "216",
        "modelo": "TRATOR JOHN DEERE 5070 E",
        "os": "117779",
        "data_entrada": "04/09/2025",
        "previsao_saida": "---",
        "prestador": "SOLO VERDE - MANUTENÇÃO AGRÍCOLA",
        "servico": "Vazamento no cachimbo do freio - (Fazenda São Paulo)",
        "liberado_por": "Arthur"
    },
    {
        "solicitante": "CASSIO ANTONIO MARTINS NASCIMENTO",
        "frota": "234",
        "modelo": "TRATO NEW HOLLAND 5.8 4W DW",
        "os": "117751",
        "data_entrada": "04/09/2025",
        "previsao_saida": "---",
        "prestador": "JOSE RENATO LEMES MARINHO 06173795990",
        "servico": "Avaliar e substituir barra de direção lado direito e barra de sustentação da grade de proteção, danificadas em colisão ocasionada pelo operador ao adormecer e atingir um poste - (Fazenda São Severino)",
        "liberado_por": "Arthur"
    },
    {
        "solicitante": "IZAIAS FRANCISCO DA SILVA",
        "frota": "197",
        "modelo": "TRATOR JOHN DEERE 5080E",
        "os": "117734",
        "data_entrada": "04/09/2025",
        "previsao_saida": "---",
        "prestador": "PEDRO PEREIRA MONTESSANI EIRELI - ME",
        "servico": "Revisar sinalização - (Fazenda São Severino)",
        "liberado_por": "Arthur"
    },
    {
        "solicitante": "ZYLTON FIGUEREDO SPIGUEL",
        "frota": "522",
        "modelo": "MOTOR VERMEL IRRIGACAO MB1935",
        "os": "117674",
        "data_entrada": "03/09/2025",
        "previsao_saida": "---",
        "prestador": "PEDRO PEREIRA MONTESSANI EIRELI - ME",
        "servico": "Verificar equipamento sem partida, já trocado as baterias porem continua sem ignição - (Fazenda São Paulo)",
        "liberado_por": "Arthur"
    },
    {
        "solicitante": "ALTIERES SOARES FERREIRA",
        "frota": "97",
        "modelo": "TRATOR JOHN DEERE 5065 4X4",
        "os": "117586",
        "data_entrada": "01/09/2025",
        "previsao_saida": "---",
        "prestador": "nan",
        "servico": "Avaliar e substituir engate do terceiro ponto, cuja carcaça foi rompida durante operação de carregamento de big bag de adubo. - (Fazenda Pedra Verde)",
        "liberado_por": "Arthur"
    },
    {
        "solicitante": "CASSIO ANTONIO MARTINS NASCIMENTO",
        "frota": "225",
        "modelo": "TRATO NEW HOLLAND 5.8 4W DW",
        "os": "117574",
        "data_entrada": "01/09/2025",
        "previsao_saida": "---",
        "prestador": "nan",
        "servico": "Folga nos terminais de direção - (Fazenda São Severino)",
        "liberado_por": "Arthur"
    },
    {
        "solicitante": "CASSIO ANTONIO MARTINS NASCIMENTO",
        "frota": "227",
        "modelo": "TRATO NEW HOLLAND 5.8 4W DW",
        "os": "117550",
        "data_entrada": "01/09/2025",
        "previsao_saida": "---",
        "prestador": "nan",
        "servico": "Folga nos terminais de direção - (Fazenda São Severino)",
        "liberado_por": "Arthur"
    },
    {
        "solicitante": "CASSIO ANTONIO MARTINS NASCIMENTO",
        "frota": "228",
        "modelo": "TRATO NEW HOLLAND 5.8 4W DW",
        "os": "117471",
        "data_entrada": "29/08/2025",
        "previsao_saida": "---",
        "prestador": "nan",
        "servico": "Verificar roda dianteira L/E com jogo (folga no terminal de direção)  (Fazenda São Severino)",
        "liberado_por": "Arthur"
    },
    {
        "solicitante": "DANILO MULARI GONZAGA",
        "frota": "165",
        "modelo": "TRATOR JOHN DEERE 6415 4X4",
        "os": "117466",
        "data_entrada": "29/08/2025",
        "previsao_saida": "---",
        "prestador": "ANDERSON DIEGO BICUDO 08122062903",
        "servico": "Vazamento de óleo no retentor do pistão do eixo dianteiro  - (Fazenda Estrela)_",
        "liberado_por": "Arthur"
    },
    {
        "solicitante": "ALTIERES SOARES FERREIRA",
        "frota": "138",
        "modelo": "TRATOR MASSEY FERGUSON 4275 4R",
        "os": "117462",
        "data_entrada": "29/08/2025",
        "previsao_saida": "---",
        "prestador": "PEDRO PEREIRA MONTESSANI EIRELI - ME",
        "servico": "Verificar sirene de ré não funciona - (Fazenda Pedra Verde)",
        "liberado_por": "Arthur"
    },
    {
        "solicitante": "ARTHUR SOUSA OLIVEIRA",
        "frota": "324",
        "modelo": "TRATOR NEW HOLANDTL5.80",
        "os": "117425",
        "data_entrada": "28/08/2025",
        "previsao_saida": "---",
        "prestador": "EQUAGRIL EQUIPAMENTOS AGRICOLAS LTDA",
        "servico": "Verificar alerta e relogio de combustível não funcionam - (Fazenda SP)",
        "liberado_por": "Arthur"
    },
    {
        "solicitante": "JOAO VITOR DUBAY DA SILVA",
        "frota": "230",
        "modelo": "TRATOR VALTRA A124L 4X4",
        "os": "117381",
        "data_entrada": "28/08/2025",
        "previsao_saida": "---",
        "prestador": "SOLO VERDE - MANUTENÇÃO AGRÍCOLA",
        "servico": "Regular sistema de freio e substituir coxins da cabine - (Fazenda Úrsula)",
        "liberado_por": "Arthur"
    },
    {
        "solicitante": "MARCIO APARECIDO CRUZ",
        "frota": "253",
        "modelo": "TRATOR JOHN DEERE 5080E",
        "os": "117359",
        "data_entrada": "27/08/2025",
        "previsao_saida": "---",
        "prestador": "COCAMAR MAQUINAS AGRICOLAS LTDA.",
        "servico": "Verificar ruído anormal na transmissão  - (Fazenda Minuano)",
        "liberado_por": "Arthur"
    },
    {
        "solicitante": "RENNAN ARCANJO CREPALDI",
        "frota": "10224",
        "modelo": "TRATOR JOHN DEERE 5080E",
        "os": "117337",
        "data_entrada": "27/08/2025",
        "previsao_saida": "---",
        "prestador": "ANDERSON DIEGO BICUDO 08122062903",
        "servico": "Trocar caixa de filtro quebrada - (Fazenda NSA) |Parado|",
        "liberado_por": "Arthur"
    },
    {
        "solicitante": "GABRIEL AUGUSTO BASSO",
        "frota": "350",
        "modelo": "TRATOR LS PLUS 90 CABINADO",
        "os": "116771",
        "data_entrada": "18/08/2025",
        "previsao_saida": "---",
        "prestador": "TAPECARIA PARANA LTDA",
        "servico": "Confeccionar capa de banco e tapete - (Pecuária)",
        "liberado_por": "Arthur"
    },
    {
        "solicitante": "JOAO PAULO DE OLIVEIRA PORTEIRO",
        "frota": "165",
        "modelo": "TRATOR JOHN DEERE 6415 4X4",
        "os": "116596",
        "data_entrada": "14/08/2025",
        "previsao_saida": "---",
        "prestador": "JOSE RENATO LEMES MARINHO 06173795990",
        "servico": "Fabricar proteção das lanternas traseiras - (Fazenda Casa Branca)",
        "liberado_por": "Arthur"
    },
    {
        "solicitante": "NATALINO ANTONIO JUSTINO",
        "frota": "245",
        "modelo": "TRATOR MASSEY FERGUSON 3307",
        "os": "116553",
        "data_entrada": "13/08/2025",
        "previsao_saida": "---",
        "prestador": "CICERO MUNIZ DA SILVA",
        "servico": "Vazamento de óleo no retentor da  TDP - (Fazenda Alvorada)",
        "liberado_por": "Arthur"
    },
    {
        "solicitante": "NATALINO ANTONIO JUSTINO",
        "frota": "44",
        "modelo": "TRATOR JOHN DEERE 6415 4X4",
        "os": "116552",
        "data_entrada": "13/08/2025",
        "previsao_saida": "---",
        "prestador": "MICHEL LEANDRO DA SILVA 02465062964",
        "servico": "Fazer fibra no capô quebrado - (Fazenda Alvorada)",
        "liberado_por": "Arthur"
    },
    {
        "solicitante": "CASSIO ANTONIO MARTINS NASCIMENTO",
        "frota": "165",
        "modelo": "TRATOR JOHN DEERE 6415 4X4",
        "os": "116337",
        "data_entrada": "08/08/2025",
        "previsao_saida": "---",
        "prestador": "PEDRO PEREIRA MONTESSANI EIRELI - ME",
        "servico": "\"Verificar cibiés de teto que não acendem. Operador já verificou conectores, fusíveis e demais componentes básicos. - (Fazenda São Severino)",
        "liberado_por": "Arthur"
    },
    {
        "solicitante": "ELISMAR SIQUEIRA DA SILVA JUNIOR",
        "frota": "70",
        "modelo": "TRATOR MASSEY FERGUSON 4275/4",
        "os": "116048",
        "data_entrada": "05/08/2025",
        "previsao_saida": "---",
        "prestador": "PEDRO PEREIRA MONTESSANI EIRELI - ME",
        "servico": "Relogio horimetro apagado, verificar possível substituição do painel - (Fazenda Nova Manhã)",
        "liberado_por": "Arthur"
    },
    {
        "solicitante": "PAULO VINICIUS DOS ANJOS DA CRUZ",
        "frota": "250",
        "modelo": "TRATOR JOHN DEERE 5080EN",
        "os": "115864",
        "data_entrada": "04/08/2025",
        "previsao_saida": "---",
        "prestador": "FERNANDA BARBOSA MORANGUEIRA 00413385965",
        "servico": "Trocar borrachas de vedação da porta e banco danificado -  (Fazenda Estrela)",
        "liberado_por": "Arthur"
    },
    {
        "solicitante": "JOAO PAULO DE OLIVEIRA PORTEIRO",
        "frota": "10217",
        "modelo": "TRATOR JOHN DEERE 5080E",
        "os": "114790",
        "data_entrada": "19/07/2025",
        "previsao_saida": "---",
        "prestador": "MICHEL LEANDRO DA SILVA 02465062964",
        "servico": "Verificar dano causado pelo escapamento que encostou no teto do trator e derreteu a estrutura. - (Fazenda Casa Branca)",
        "liberado_por": "Arthur"
    }
]