[
    {
        "solicitante": "ZYLTON FIGUEREDO SPIGUEL",
        "frota": "5784",
        "modelo": "DESENROLADOR DE MANGUEIRA",
        "os": "114180",
        "data_entrada": "11/07/2025",
        "previsao_saida": "---",
        "prestador": "nan",
        "servico": "Reforçar suporte inferior trincado e substituir as tábuas laterais danificadas do desenrolador de mangueira de gotejo. - (Fazenda Minuano)",
        "liberado_por": "Mauricio"
    },
    {
        "solicitante": "ANTONIO PAULO LARENTIS ALVES",
        "frota": "81",
        "modelo": "TRATOR JOHN DEERE 5403 4X4",
        "os": "114176",
        "data_entrada": "11/07/2025",
        "previsao_saida": "---",
        "prestador": "RIVELINO LONGATO 03100998979",
        "servico": "Pneu dianteiro L/D furado - (Fazenda Minuano)",
        "liberado_por": "Mauricio"
    },
    {
        "solicitante": "MURILO J ONCK LEMES DA SILVA",
        "frota": "5785",
        "modelo": "GUINCHO AGRICOL TATU GATG 2000",
        "os": "114166",
        "data_entrada": "11/07/2025",
        "previsao_saida": "---",
        "prestador": "JOSE RENATO LEMES MARINHO 06173795990",
        "servico": "Trocar ganho do guincho - (Fazenda Bela Manhã)",
        "liberado_por": "Mauricio"
    },
    {
        "solicitante": "LEOJABES GUIMARAES SOUZA NASCIMENTO",
        "frota": "5804",
        "modelo": "PULVERIZADOR FMC 4000 BILATERA",
        "os": "114164",
        "data_entrada": "11/07/2025",
        "previsao_saida": "---",
        "prestador": "nan",
        "servico": "Verificar funcionamento do comando hidráulico.",
        "liberado_por": "Mauricio"
    },
    {
        "solicitante": "NATALINO ANTONIO JUSTINO",
        "frota": "5426",
        "modelo": "MOTOSERRA",
        "os": "114159",
        "data_entrada": "11/07/2025",
        "previsao_saida": "---",
        "prestador": "MORENA - MAQUINAS E FERRAGENS",
        "servico": "Fazer revisão - (Fazenda Alvorada)",
        "liberado_por": "Mauricio"
    },
    {
        "solicitante": "JOAO PAULO DE OLIVEIRA PORTEIRO",
        "frota": "5261",
        "modelo": "PULVERIZADOR 2000 LT",
        "os": "114157",
        "data_entrada": "11/07/2025",
        "previsao_saida": "---",
        "prestador": "JOSE RENATO LEMES MARINHO 06173795990",
        "servico": "Soldar trinca no chassi - (Fazenda Casa Branca)",
        "liberado_por": "Mauricio"
    },
    {
        "solicitante": "NATALINO ANTONIO JUSTINO",
        "frota": "5709",
        "modelo": "TRINCHA LEVE ARTI. TRLA 180H",
        "os": "114147",
        "data_entrada": "11/07/2025",
        "previsao_saida": "---",
        "prestador": "GILSON CESAR ALVES DOS SANTOS 660964809",
        "servico": "Quebra do pino do engate do braço hidráulico - (Fazenda Alvorada)",
        "liberado_por": "Mauricio"
    },
    {
        "solicitante": "RENNAN ARCANJO CREPALDI",
        "frota": "259",
        "modelo": "TRATOR JOHN DEERE 5080E",
        "os": "114145",
        "data_entrada": "11/07/2025",
        "previsao_saida": "---",
        "prestador": "RIVELINO LONGATO 03100998979",
        "servico": "Pneu L/D dianteiro furado - (Fazenda NSA)",
        "liberado_por": "Mauricio"
    },
    {
        "solicitante": "RENNAN ARCANJO CREPALDI",
        "frota": "5718",
        "modelo": "PULVERIZADOR FMC 4000 BILATERA",
        "os": "114143",
        "data_entrada": "11/07/2025",
        "previsao_saida": "---",
        "prestador": "JOSE RENATO LEMES MARINHO 06173795990",
        "servico": "Asa L/D torta - (Fazenda NSA)",
        "liberado_por": "Mauricio"
    },
    {
        "solicitante": "NATALINO ANTONIO JUSTINO",
        "frota": "5035",
        "modelo": "ATOMIZADOR FMC 4000 LT",
        "os": "114139",
        "data_entrada": "11/07/2025",
        "previsao_saida": "---",
        "prestador": "RIVELINO LONGATO 03100998979",
        "servico": "Pneu L/D deslocado - (Fazenda Alvorada)",
        "liberado_por": "Mauricio"
    },
    {
        "solicitante": "JOAO PAULO DE OLIVEIRA PORTEIRO",
        "frota": "5365",
        "modelo": "PULVERIZADOR 4000 LT - NATALI",
        "os": "114131",
        "data_entrada": "11/07/2025",
        "previsao_saida": "---",
        "prestador": "IAGO MANUNTENCAO AGRICOLA LTDA",
        "servico": "Trocar correia do agitador de calda - (Fazenda Casa Branca)",
        "liberado_por": "Mauricio"
    },
    {
        "solicitante": "ROMES ROSA SILVA",
        "frota": "5403",
        "modelo": "PULVERIZADOR GULIVER 4000",
        "os": "114121",
        "data_entrada": "10/07/2025",
        "previsao_saida": "---",
        "prestador": "MATEUS APARECIDO DE LIMA SANTOS",
        "servico": "Vazamento nas canecas (Fazenda São Pedro)",
        "liberado_por": "Mauricio"
    },
    {
        "solicitante": "JOAO VITOR DUBAY DA SILVA",
        "frota": "5105",
        "modelo": "GRADE ARADORA C.CONTROLE BALDA",
        "os": "114119",
        "data_entrada": "10/07/2025",
        "previsao_saida": "---",
        "prestador": "JOSE RENATO LEMES MARINHO 06173795990",
        "servico": "Verificar rolamentos das duas rodas da grade. (Fazenda Úrsula)",
        "liberado_por": "Mauricio"
    },
    {
        "solicitante": "GABRIEL AUGUSTO BASSO",
        "frota": "5067",
        "modelo": "ADUBADEIRA CACAMBA TATU",
        "os": "114118",
        "data_entrada": "10/07/2025",
        "previsao_saida": "---",
        "prestador": "GILSON CESAR ALVES DOS SANTOS 660964809",
        "servico": "Realizar troca do pé de apoio (Fazenda Pecuária)",
        "liberado_por": "Mauricio"
    },
    {
        "solicitante": "LEOJABES GUIMARAES SOUZA NASCIMENTO",
        "frota": "5048",
        "modelo": "ATOMIZADOR FMC 4000 LT",
        "os": "114117",
        "data_entrada": "10/07/2025",
        "previsao_saida": "---",
        "prestador": "GILSON CESAR ALVES DOS SANTOS 660964809",
        "servico": "Soldar câmera de compressão (Fazenda São Paulo)",
        "liberado_por": "Mauricio"
    },
    {
        "solicitante": "PAULO VINICIUS DOS ANJOS DA CRUZ",
        "frota": "5671",
        "modelo": "PULV.BARRA SUBCOPA DUPLA FRON",
        "os": "114115",
        "data_entrada": "10/07/2025",
        "previsao_saida": "---",
        "prestador": "nan",
        "servico": "Conferir a solenoide da barra de herbicida. (Fazenda Estrela)",
        "liberado_por": "Mauricio"
    },
    {
        "solicitante": "CASSIO ANTONIO MARTINS NASCIMENTO",
        "frota": "5599",
        "modelo": "PREMIX PRIME 2T 2000",
        "os": "114105",
        "data_entrada": "10/07/2025",
        "previsao_saida": "---",
        "prestador": "IAGO MANUNTENCAO AGRICOLA LTDA",
        "servico": "Rosca do premix estragada. (Fazenda São Severino)",
        "liberado_por": "Mauricio"
    },
    {
        "solicitante": "JOAO PAULO DE OLIVEIRA PORTEIRO",
        "frota": "5100",
        "modelo": "GUINCHO HIDRAULICO",
        "os": "114102",
        "data_entrada": "10/07/2025",
        "previsao_saida": "---",
        "prestador": "JOSE RENATO LEMES MARINHO 06173795990",
        "servico": "Soldar argola do bg, e soldar trincas no chassi (Fazenda Casa Branca)",
        "liberado_por": "Mauricio"
    },
    {
        "solicitante": "ANTONIO PAULO LARENTIS ALVES",
        "frota": "5749",
        "modelo": "PULVERIZADOR FMC 4000 BILATERA",
        "os": "114094",
        "data_entrada": "10/07/2025",
        "previsao_saida": "---",
        "prestador": "IAGO MANUNTENCAO AGRICOLA LTDA",
        "servico": "Vazamento nas canecas (Fazenda Minuano)",
        "liberado_por": "Mauricio"
    },
    {
        "solicitante": "LEOJABES GUIMARAES SOUZA NASCIMENTO",
        "frota": "5804",
        "modelo": "PULVERIZADOR FMC 4000 BILATERA",
        "os": "114091",
        "data_entrada": "10/07/2025",
        "previsao_saida": "---",
        "prestador": "nan",
        "servico": "Soldar fio do terminal do SPE (Fazenda São Paulo)",
        "liberado_por": "Mauricio"
    },
    {
        "solicitante": "LEOJABES GUIMARAES SOUZA NASCIMENTO",
        "frota": "5803",
        "modelo": "PULVERIZADOR FMC 4000 BILATERA",
        "os": "114090",
        "data_entrada": "10/07/2025",
        "previsao_saida": "---",
        "prestador": "nan",
        "servico": "Soldar fio do terminal do SPE (Fazenda São Paulo)",
        "liberado_por": "Mauricio"
    },
    {
        "solicitante": "CARLOS HENRIQUE LEITE DONATO",
        "frota": "5107",
        "modelo": "ATOMIZADOR FMC COPLING 4000 LT",
        "os": "114051",
        "data_entrada": "10/07/2025",
        "previsao_saida": "---",
        "prestador": "IAGO MANUNTENCAO AGRICOLA LTDA",
        "servico": "Rolamento da turbina roncando - (Fazenda Estrela)",
        "liberado_por": "Mauricio"
    },
    {
        "solicitante": "RENNAN ARCANJO CREPALDI",
        "frota": "5724",
        "modelo": "PULV.BARRA SUBCOPA DUPLA FRON",
        "os": "114017",
        "data_entrada": "09/07/2025",
        "previsao_saida": "---",
        "prestador": "JOSE RENATO LEMES MARINHO 06173795990",
        "servico": "Instalar esticador e batedor e realinha barrinha - (Fazenda NSA)",
        "liberado_por": "Mauricio"
    },
    {
        "solicitante": "PAULO VINICIUS DOS ANJOS DA CRUZ",
        "frota": "5367",
        "modelo": "PULVERIZADOR 4000 LT - NATALI",
        "os": "114006",
        "data_entrada": "09/07/2025",
        "previsao_saida": "---",
        "prestador": "GILSON CESAR ALVES DOS SANTOS",
        "servico": "Fazer solda em trincas na estrutura - (Fazenda Estrela)",
        "liberado_por": "Mauricio"
    },
    {
        "solicitante": "PAULO VINICIUS DOS ANJOS DA CRUZ",
        "frota": "5367",
        "modelo": "PULVERIZADOR 4000 LT - NATALI",
        "os": "114005",
        "data_entrada": "09/07/2025",
        "previsao_saida": "---",
        "prestador": "nan",
        "servico": "Inspecionar e reparar vazamento de óleo na bomba hidráulica responsável pelo sistema de abertura e fechamento da pistopleira. - (Fazenda Estrela)",
        "liberado_por": "Mauricio"
    },
    {
        "solicitante": "EDER JOSE FERNANDES DE ALMEIDA",
        "frota": "5657",
        "modelo": "PULVERIZADOR 4000 LT JACTO",
        "os": "114000",
        "data_entrada": "09/07/2025",
        "previsao_saida": "---",
        "prestador": "IAGO MANUNTENCAO AGRICOLA LTDA",
        "servico": "Realizar o realinhamento do ramal que ficou torto após queda em depressão no solo - (Fazenda Terra Branca)",
        "liberado_por": "Mauricio"
    },
    {
        "solicitante": "EDER JOSE FERNANDES DE ALMEIDA",
        "frota": "5399",
        "modelo": "PULVERIZADOR 4000 LT - NATALI",
        "os": "113999",
        "data_entrada": "09/07/2025",
        "previsao_saida": "---",
        "prestador": "IAGO MANUNTENCAO AGRICOLA LTDA",
        "servico": "Quebra do rolamento do eixo da bomba - (Fazenda Terra Branca)",
        "liberado_por": "Mauricio"
    },
    {
        "solicitante": "EDER JOSE FERNANDES DE ALMEIDA",
        "frota": "5557",
        "modelo": "ROCADEIRA KAMAQ",
        "os": "113997",
        "data_entrada": "09/07/2025",
        "previsao_saida": "---",
        "prestador": "JOSE RENATO LEMES MARINHO 06173795990",
        "servico": "Trinca na estrutura da torre - (Fazenda Terra Branca)",
        "liberado_por": "Mauricio"
    },
    {
        "solicitante": "PAULO EDSON ABREU VILELA JUNIOR",
        "frota": "5637",
        "modelo": "PODADEIRA HIDRAUTEC HLC 4",
        "os": "113995",
        "data_entrada": "09/07/2025",
        "previsao_saida": "---",
        "prestador": "M G VEDACOES E PECAS LTDA",
        "servico": "Substituir o manômetro (relógio de pressão) danificado da podadeira o qual foi quebrado durante operação ao atingir galhos. Além da substituição, confeccionar e instalar um suporte de proteção para evitar danos futuros no local - (Fazenda Nova Manhã)",
        "liberado_por": "Mauricio"
    },
    {
        "solicitante": "DANILO MULARI GONZAGA",
        "frota": "165",
        "modelo": "TRATOR JOHN DEERE 6415 4X4",
        "os": "113994",
        "data_entrada": "09/07/2025",
        "previsao_saida": "---",
        "prestador": "nan",
        "servico": "Instalar sistema eletrico do motor do para-brisa - (Fazenda Estrela)",
        "liberado_por": "Mauricio"
    },
    {
        "solicitante": "RENNAN ARCANJO CREPALDI",
        "frota": "5502",
        "modelo": "PULVERIZADOR FMC 4000 BILATERA",
        "os": "113989",
        "data_entrada": "09/07/2025",
        "previsao_saida": "---",
        "prestador": "nan",
        "servico": "Troca das correias e rolamento da  turbina - (Fazenda NSA)",
        "liberado_por": "Mauricio"
    },
    {
        "solicitante": "RENNAN ARCANJO CREPALDI",
        "frota": "5009",
        "modelo": "ATOMIZADOR FMC 4000 LT",
        "os": "113988",
        "data_entrada": "09/07/2025",
        "previsao_saida": "---",
        "prestador": "JOSE RENATO LEMES MARINHO 06173795990",
        "servico": "Fazer solda em trinca no chassi - (Fazenda NSA)",
        "liberado_por": "Mauricio"
    },
    {
        "solicitante": "RENNAN ARCANJO CREPALDI",
        "frota": "5009",
        "modelo": "ATOMIZADOR FMC 4000 LT",
        "os": "113987",
        "data_entrada": "09/07/2025",
        "previsao_saida": "---",
        "prestador": "55.387.737 MICHEL LEANDRO DA SILVA",
        "servico": "Fazer fibra em trincas na estrutura da torre - (Fazenda NSA)",
        "liberado_por": "Mauricio"
    },
    {
        "solicitante": "ANTONIO PAULO LARENTIS ALVES",
        "frota": "253",
        "modelo": "TRATOR JOHN DEERE 5080E",
        "os": "113970",
        "data_entrada": "08/07/2025",
        "previsao_saida": "---",
        "prestador": "RIVELINO LONGATO 03100998979",
        "servico": "Pneu traseiro L/D - (Fazenda Minuano)",
        "liberado_por": "Mauricio"
    },
    {
        "solicitante": "CARLOS HENRIQUE LEITE DONATO",
        "frota": "5451",
        "modelo": "PULVERIZADOR BARRAS TRICICLO",
        "os": "113965",
        "data_entrada": "08/07/2025",
        "previsao_saida": "---",
        "prestador": "IAGO MANUNTENCAO AGRICOLA LTDA",
        "servico": "Revisar relação - (Fazenda Estrela)",
        "liberado_por": "Mauricio"
    },
    {
        "solicitante": "EDER JOSE FERNANDES DE ALMEIDA",
        "frota": "5398",
        "modelo": "PULVERIZADOR 4000 LT - NATALI",
        "os": "113963",
        "data_entrada": "08/07/2025",
        "previsao_saida": "---",
        "prestador": "F MAGALHAES",
        "servico": "Confeccionar ramal para distribuição dos bicos do SPE - (Fazenda Terra Branca)",
        "liberado_por": "Mauricio"
    },
    {
        "solicitante": "EDER JOSE FERNANDES DE ALMEIDA",
        "frota": "5399",
        "modelo": "PULVERIZADOR 4000 LT - NATALI",
        "os": "113962",
        "data_entrada": "08/07/2025",
        "previsao_saida": "---",
        "prestador": "F MAGALHAES",
        "servico": "Confeccionar ramal para distribuição dos bicos do SPE - (Fazenda Terra Branca)",
        "liberado_por": "Mauricio"
    },
    {
        "solicitante": "MURILO J ONCK LEMES DA SILVA",
        "frota": "5355",
        "modelo": "ATOMIZADOR JACTO 4000 LT",
        "os": "113958",
        "data_entrada": "08/07/2025",
        "previsao_saida": "---",
        "prestador": "RIVELINO LONGATO 03100998979",
        "servico": "Pneu L/D furado - (Fazenda Santa Izabel)",
        "liberado_por": "Mauricio"
    },
    {
        "solicitante": "ROMES ROSA SILVA",
        "frota": "5760",
        "modelo": "PULVERIZADOR 4000 SMART DUPLO",
        "os": "113924",
        "data_entrada": "08/07/2025",
        "previsao_saida": "---",
        "prestador": "MATEUS APARECIDO DE LIMA SANTOS",
        "servico": "Vazamento no cilindro do pistão torno  - (Fazenda São Pedro)",
        "liberado_por": "Mauricio"
    },
    {
        "solicitante": "LEOJABES GUIMARAES SOUZA NASCIMENTO",
        "frota": "5504",
        "modelo": "PUL.TURBO 4000 NATALI ALFA",
        "os": "113906",
        "data_entrada": "08/07/2025",
        "previsao_saida": "---",
        "prestador": "IAGO MANUNTENCAO AGRICOLA LTDA",
        "servico": "Substituição dos registros do sistema do tanque de pulverização - (Fazenda São Paulo)",
        "liberado_por": "Mauricio"
    },
    {
        "solicitante": "ROMES ROSA SILVA",
        "frota": "5126",
        "modelo": "ADUBADEIRA KAMAQ 1500 KG",
        "os": "113901",
        "data_entrada": "08/07/2025",
        "previsao_saida": "---",
        "prestador": "MATEUS APARECIDO DE LIMA SANTOS",
        "servico": "Verificar rolamento dos pratos e quebra do pino elástico - (Fazenda São Pedro)",
        "liberado_por": "Mauricio"
    },
    {
        "solicitante": "GABRIEL AUGUSTO BASSO",
        "frota": "187",
        "modelo": "PA CARREGADEIRA 924K",
        "os": "113900",
        "data_entrada": "08/07/2025",
        "previsao_saida": "---",
        "prestador": "RIVELINO LONGATO 03100998979",
        "servico": "Calibrar pneu L/D traseiro e verificar calibragem dos demais pneus - (Pecuaria)",
        "liberado_por": "Mauricio"
    },
    {
        "solicitante": "GABRIEL AUGUSTO BASSO",
        "frota": "5352",
        "modelo": "ADUBADEIRA DCCO 10500 S-0114",
        "os": "113899",
        "data_entrada": "08/07/2025",
        "previsao_saida": "---",
        "prestador": "RIVELINO LONGATO 03100998979",
        "servico": "Verificar perda de parafusos de uma das rodas, que ocasionou a parada do equipamento. Realizar inspeção completa, providenciar substituição dos parafusos e checagem geral para garantir segurança na operação - (Pecuaria)",
        "liberado_por": "Mauricio"
    },
    {
        "solicitante": "LEOJABES GUIMARAES SOUZA NASCIMENTO",
        "frota": "5542",
        "modelo": "DISTRIBUIDOR FARTUS 8.0 GRANEL",
        "os": "113898",
        "data_entrada": "08/07/2025",
        "previsao_saida": "---",
        "prestador": "RIVELINO LONGATO 03100998979",
        "servico": "Pneu L/D dianteiro furado - (Fazenda São Paulo)",
        "liberado_por": "Mauricio"
    },
    {
        "solicitante": "ELISMAR SIQUEIRA DA SILVA JUNIOR",
        "frota": "5600",
        "modelo": "ATOMIZADOR NATALI 4000 LT",
        "os": "113896",
        "data_entrada": "08/07/2025",
        "previsao_saida": "---",
        "prestador": "IAGO MANUNTENCAO AGRICOLA LTDA",
        "servico": "Verificar vazamento no retentor da bomba, avaliar motivo do desalinhamento ou salto da correia e acertar parafuso de ajuste da correia da turbina - (Fazenda Nova Manhã)",
        "liberado_por": "Mauricio"
    },
    {
        "solicitante": "JOAO PAULO DE OLIVEIRA PORTEIRO",
        "frota": "5559",
        "modelo": "PODADEIRA HIDRAUTEC HLC6",
        "os": "113891",
        "data_entrada": "07/07/2025",
        "previsao_saida": "---",
        "prestador": "M G VEDACOES E PECAS LTDA",
        "servico": "Quebra da corrente do sistema de transmissão e parafusos que seguram o rotor - (Fazenda Casa Branca)",
        "liberado_por": "Mauricio"
    },
    {
        "solicitante": "CARLOS HENRIQUE LEITE DONATO",
        "frota": "5748",
        "modelo": "PULVERIZADOR FMC 4000 BILATERA",
        "os": "113866",
        "data_entrada": "07/07/2025",
        "previsao_saida": "---",
        "prestador": "MICHEL LEANDRO DA SILVA 02465062964",
        "servico": "Fazer fibra na base turbina - (Fazenda Estrela)",
        "liberado_por": "Mauricio"
    },
    {
        "solicitante": "ANTONIO PAULO LARENTIS ALVES",
        "frota": "144",
        "modelo": "TRATOR MASSEY FERGUSON 4275 4R",
        "os": "113837",
        "data_entrada": "07/07/2025",
        "previsao_saida": "---",
        "prestador": "RIVELINO LONGATO 03100998979",
        "servico": "Pneu dianteiro L/E furado - (Fazenda Minuano)",
        "liberado_por": "Mauricio"
    },
    {
        "solicitante": "IZAIAS FRANCISCO DA SILVA",
        "frota": "193",
        "modelo": "TRATOR NEW HOLAND TL 5.80",
        "os": "113754",
        "data_entrada": "04/07/2025",
        "previsao_saida": "---",
        "prestador": "RIVELINO LONGATO 03100998979",
        "servico": "Pneu dianteiro L/E furado - (Fazenda Estrela)",
        "liberado_por": "Mauricio"
    },
    {
        "solicitante": "MURILO J ONCK LEMES DA SILVA",
        "frota": "5697",
        "modelo": "PULVERIZADOR 2000 LT",
        "os": "113752",
        "data_entrada": "04/07/2025",
        "previsao_saida": "---",
        "prestador": "RIVELINO LONGATO 03100998979",
        "servico": "Pneu L/D furado - (Fazenda Bela Manhã)",
        "liberado_por": "Mauricio"
    },
    {
        "solicitante": "JOAO VITOR DUBAY DA SILVA",
        "frota": "5014",
        "modelo": "PULVERIZADOR COLUMBIA 2000 LT",
        "os": "113751",
        "data_entrada": "04/07/2025",
        "previsao_saida": "---",
        "prestador": "GILSON CESAR ALVES DOS SANTOS",
        "servico": "Fazer solda em trinca no chassi - (Fazenda NSA)",
        "liberado_por": "Mauricio"
    },
    {
        "solicitante": "NATALINO ANTONIO JUSTINO",
        "frota": "5035",
        "modelo": "ATOMIZADOR FMC 4000 LT",
        "os": "113748",
        "data_entrada": "04/07/2025",
        "previsao_saida": "---",
        "prestador": "55.387.737 MICHEL LEANDRO DA SILVA",
        "servico": "Verificar vazamento na estrutura de fibra do tanque. Avaliar a origem e necessidade de reparo. - (Fazenda Alvorada)",
        "liberado_por": "Mauricio"
    },
    {
        "solicitante": "ROMES ROSA SILVA",
        "frota": "5421",
        "modelo": "PULVERIZADOR GULIVER 4000",
        "os": "113728",
        "data_entrada": "03/07/2025",
        "previsao_saida": "---",
        "prestador": "JOSE RENATO LEMES MARINHO 06173795990",
        "servico": "Fazer solda em trinca no chassi - (Fazenda São Pedro)",
        "liberado_por": "Mauricio"
    },
    {
        "solicitante": "MARCIO JUNIO NUNES DE OLIVEIRA",
        "frota": "5489",
        "modelo": "CONJUNTO PODADOR WWD",
        "os": "113722",
        "data_entrada": "03/07/2025",
        "previsao_saida": "---",
        "prestador": "M G VEDACOES E PECAS LTDA",
        "servico": "Substituir parafuso de fixação das réguas ao rotor do conjunto podador WWD, devido à quebra do componente, comprometendo a fixação e o funcionamento do sistema de corte - (Fazenda São Severino)",
        "liberado_por": "Mauricio"
    },
    {
        "solicitante": "ALTIERES SOARES FERREIRA",
        "frota": "5604",
        "modelo": "ATOMIZADOR FMC COPLING 4000 LT",
        "os": "113713",
        "data_entrada": "03/07/2025",
        "previsao_saida": "---",
        "prestador": "M S BORRACHARIA - MARCELO SOUZA SOBRINHO",
        "servico": "Substituir rolamento do mancal do eixo da bomba, que se encontra quebrado - (Fazenda Pedra Verde)",
        "liberado_por": "Mauricio"
    },
    {
        "solicitante": "DANILO MULARI GONZAGA",
        "frota": "5494",
        "modelo": "ADUBADEIRA DCA2 7500 S-0118",
        "os": "113710",
        "data_entrada": "03/07/2025",
        "previsao_saida": "---",
        "prestador": "IAGO MANUNTENCAO AGRICOLA LTDA",
        "servico": "Substituir rolamento do eixo do multiplicador, devido a desgaste - (Fazenda Estrela)",
        "liberado_por": "Mauricio"
    },
    {
        "solicitante": "DANILO MULARI GONZAGA",
        "frota": "5044",
        "modelo": "GUINCHO HIDRAULICO REFORCADO",
        "os": "113690",
        "data_entrada": "03/07/2025",
        "previsao_saida": "---",
        "prestador": "JOSE RENATO LEMES MARINHO 06173795990",
        "servico": "Substituir eixo da cabeça do guincho, devido a desgaste ou quebra, garantindo o pleno funcionamento do sistema de elevação. - (Fazenda Estrela)",
        "liberado_por": "Mauricio"
    },
    {
        "solicitante": "ANTONIO PAULO LARENTIS ALVES",
        "frota": "254",
        "modelo": "TRATOR JOHN DEERE 5080E",
        "os": "113685",
        "data_entrada": "03/07/2025",
        "previsao_saida": "---",
        "prestador": "nan",
        "servico": "Verificar vazamento de diesel na base da bomba injetora - (Fazenda Minuano)",
        "liberado_por": "Mauricio"
    },
    {
        "solicitante": "NATALINO ANTONIO JUSTINO",
        "frota": "5155",
        "modelo": "ATOMIZADOR FMC 4000 LT",
        "os": "113684",
        "data_entrada": "03/07/2025",
        "previsao_saida": "---",
        "prestador": "RIVELINO LONGATO 03100998979",
        "servico": "Pneu L/D estourado - (Fazenda Alvorada)",
        "liberado_por": "Mauricio"
    },
    {
        "solicitante": "NATALINO ANTONIO JUSTINO",
        "frota": "5035",
        "modelo": "ATOMIZADOR FMC 4000 LT",
        "os": "113682",
        "data_entrada": "03/07/2025",
        "previsao_saida": "---",
        "prestador": "MATEUS APARECIDO DE LIMA SANTOS",
        "servico": "Verificar quebra da ponta de eixo da roda - (Fazenda Alvorada)",
        "liberado_por": "Mauricio"
    },
    {
        "solicitante": "ALTIERES SOARES FERREIRA",
        "frota": "5135",
        "modelo": "PULVERIZADOR 2000 LT FMC",
        "os": "113680",
        "data_entrada": "02/07/2025",
        "previsao_saida": "---",
        "prestador": "nan",
        "servico": "Verificar vazamento na bomba KPL 160 e realizar substituição dos reparos - (Fazenda Pedra Verde)",
        "liberado_por": "Mauricio"
    },
    {
        "solicitante": "RENNAN ARCANJO CREPALDI",
        "frota": "5229",
        "modelo": "PODADEIRA HIDRAUTEC HLC 3",
        "os": "113679",
        "data_entrada": "02/07/2025",
        "previsao_saida": "---",
        "prestador": "M G VEDACOES E PECAS LTDA",
        "servico": "Verificar barra de corte danificada - (Fazenda NSA)",
        "liberado_por": "Mauricio"
    },
    {
        "solicitante": "ANTONIO PAULO LARENTIS ALVES",
        "frota": "81",
        "modelo": "TRATOR JOHN DEERE 5403 4X4",
        "os": "113677",
        "data_entrada": "02/07/2025",
        "previsao_saida": "---",
        "prestador": "RIVELINO LONGATO 03100998979",
        "servico": "Pneu L/E dianteiro furado - (Fazenda Minuano)",
        "liberado_por": "Mauricio"
    },
    {
        "solicitante": "ROMES ROSA SILVA",
        "frota": "5739",
        "modelo": "ROCADEIRA RC2 E 3100 S0516",
        "os": "113659",
        "data_entrada": "02/07/2025",
        "previsao_saida": "---",
        "prestador": "MATEUS APARECIDO DE LIMA SANTOS",
        "servico": "Verificar folga no eixo da roda guia  - (Fazenda São Pedro)",
        "liberado_por": "Mauricio"
    },
    {
        "solicitante": "LEOJABES GUIMARAES SOUZA NASCIMENTO",
        "frota": "5347",
        "modelo": "ADUBADEIRA DCA2 7500 S-0118",
        "os": "113652",
        "data_entrada": "02/07/2025",
        "previsao_saida": "---",
        "prestador": "RIVELINO LONGATO 03100998979",
        "servico": "Pneu L/E furado traseiro - (Fazenda SP)",
        "liberado_por": "Mauricio"
    },
    {
        "solicitante": "DANILO MULARI GONZAGA",
        "frota": "5667",
        "modelo": "PODADEIRA HIDRAUTEC HLD1",
        "os": "113650",
        "data_entrada": "02/07/2025",
        "previsao_saida": "---",
        "prestador": "M G VEDACOES E PECAS LTDA",
        "servico": "Avaliar e corrigir vazamento de óleo na saída da caixa de comando. - (Fazenda Estrela)",
        "liberado_por": "Mauricio"
    },
    {
        "solicitante": "ADRIANO CLAUDIO FIRMINO",
        "frota": "92",
        "modelo": "TRATOR JOHN DEERE 5065 4X4",
        "os": "113633",
        "data_entrada": "02/07/2025",
        "previsao_saida": "---",
        "prestador": "SIDNEI LUQUES NUNES BORRACHARIA",
        "servico": "Pneu dianteiro L/D furado - (Fazenda Nova Manhã)",
        "liberado_por": "Mauricio"
    },
    {
        "solicitante": "MURILO J ONCK LEMES DA SILVA",
        "frota": "5697",
        "modelo": "PULVERIZADOR 2000 LT",
        "os": "113632",
        "data_entrada": "02/07/2025",
        "previsao_saida": "---",
        "prestador": "IAGO MANUNTENCAO AGRICOLA LTDA",
        "servico": "Verificar vazamento de óleo na bomba -  (Fazenda Bela Manhã)",
        "liberado_por": "Mauricio"
    },
    {
        "solicitante": "JOSIMAR BADIAS DE JESUS",
        "frota": "10216",
        "modelo": "TRATOR JOHN DEERE 5080E",
        "os": "113637",
        "data_entrada": "02/07/2025",
        "previsao_saida": "---",
        "prestador": "RIVELINO LONGATO 03100998979",
        "servico": "Pneu dianteiro L/D furado - (Fazenda São Pedro)",
        "liberado_por": "Mauricio"
    },
    {
        "solicitante": "JOAO VITOR DUBAY DA SILVA",
        "frota": "5014",
        "modelo": "PULVERIZADOR COLUMBIA 2000 LT",
        "os": "113606",
        "data_entrada": "01/07/2025",
        "previsao_saida": "---",
        "prestador": "RIVELINO LONGATO 03100998979",
        "servico": "Trocar pneu L/D 9.5-24 danificado - (Fazenda NSA)",
        "liberado_por": "Mauricio"
    },
    {
        "solicitante": "ROMES ROSA SILVA",
        "frota": "5676",
        "modelo": "PULV.BARRA SUBCOPA DUPLA FRON",
        "os": "113602",
        "data_entrada": "01/07/2025",
        "previsao_saida": "---",
        "prestador": "GILSON CESAR ALVES DOS SANTOS",
        "servico": "Vazamento nos pistões da barra e nas válvulas do comando  - (Fazenda São Pedro)",
        "liberado_por": "Mauricio"
    },
    {
        "solicitante": "ROMES ROSA SILVA",
        "frota": "5726",
        "modelo": "PULV.BARRA SUBCOPA DUPLA FRON",
        "os": "113601",
        "data_entrada": "01/07/2025",
        "previsao_saida": "---",
        "prestador": "GILSON CESAR ALVES DOS SANTOS",
        "servico": "Vazamento de óleo nas válvulas do comando - (Fazenda São Pedro)",
        "liberado_por": "Mauricio"
    },
    {
        "solicitante": "JOAO VITOR DUBAY DA SILVA",
        "frota": "279",
        "modelo": "TRATOR VALTRA T250 CVT",
        "os": "113599",
        "data_entrada": "01/07/2025",
        "previsao_saida": "---",
        "prestador": "RIVELINO LONGATO 03100998979",
        "servico": "Pneu Dianteiro L/E (Fazenda Nova (Vo Gabi )",
        "liberado_por": "Mauricio"
    },
    {
        "solicitante": "ADRIANO CLAUDIO FIRMINO",
        "frota": "5610",
        "modelo": "PODADEIRA HIDRAUTEC HLC 4",
        "os": "113587",
        "data_entrada": "01/07/2025",
        "previsao_saida": "---",
        "prestador": "M G VEDACOES E PECAS LTDA",
        "servico": "Montar a podadeira dupla traseira - (Fazenda Nova Manhã)",
        "liberado_por": "Mauricio"
    },
    {
        "solicitante": "RENNAN ARCANJO CREPALDI",
        "frota": "5778",
        "modelo": "DISTRIBUIDOR FARTUS 8.0 GRANEL",
        "os": "113581",
        "data_entrada": "01/07/2025",
        "previsao_saida": "---",
        "prestador": "GRANEL IMPLEMENTOS AGRICOLA LTDA",
        "servico": "Verificar quebra da esteira da adubadeira, comprometendo o transporte e a distribuição do insumo. - (Fazenda NSA)",
        "liberado_por": "Mauricio"
    },
    {
        "solicitante": "IZAIAS FRANCISCO DA SILVA",
        "frota": "5571",
        "modelo": "CARRETA TRANSBORDO GTM",
        "os": "113580",
        "data_entrada": "01/07/2025",
        "previsao_saida": "---",
        "prestador": "RIVELINO LONGATO 03100998979",
        "servico": "Pneu dianteiro L/E furado - (Fazenda Santa Luiza)",
        "liberado_por": "Mauricio"
    },
    {
        "solicitante": "JOAO VITOR DUBAY DA SILVA",
        "frota": "5099",
        "modelo": "GRADE NIVELADORA DE CONTROLE",
        "os": "113561",
        "data_entrada": "01/07/2025",
        "previsao_saida": "---",
        "prestador": "JOSE RENATO LEMES MARINHO 06173795990",
        "servico": "Realizar revisão completa no equipamento, devido à quebra de mancais e discos. - (Fazenda Bela Manhã)",
        "liberado_por": "Mauricio"
    },
    {
        "solicitante": "ROMES ROSA SILVA",
        "frota": "5415",
        "modelo": "MOTOSERRA",
        "os": "113558",
        "data_entrada": "01/07/2025",
        "previsao_saida": "---",
        "prestador": "DOUTORMAQ PECAS E SERVICOS LTDA",
        "servico": "Constatado travamento do conjunto motriz da motosserra (fusão do motor), com comprometimento total dos componentes internos - (Fazenda São Pedro)",
        "liberado_por": "Mauricio"
    },
    {
        "solicitante": "NATALINO ANTONIO JUSTINO",
        "frota": "5572",
        "modelo": "CARRETA TRANSBORDO GTM",
        "os": "113567",
        "data_entrada": "01/07/2025",
        "previsao_saida": "---",
        "prestador": "GILSON CESAR ALVES DOS SANTOS",
        "servico": "Trocar reparo da bica - (Fazenda Alvorada)",
        "liberado_por": "Mauricio"
    },
    {
        "solicitante": "IZAIAS FRANCISCO DA SILVA",
        "frota": "5571",
        "modelo": "CARRETA TRANSBORDO GTM",
        "os": "113495",
        "data_entrada": "30/06/2025",
        "previsao_saida": "---",
        "prestador": "RIVELINO LONGATO 03100998979",
        "servico": "Pneu L/D furado - (Fazenda Santa Luiza)",
        "liberado_por": "Mauricio"
    },
    {
        "solicitante": "ROMES ROSA SILVA",
        "frota": "5404",
        "modelo": "ROCADEIRA RC2 E 4500 TATU",
        "os": "113300",
        "data_entrada": "26/06/2025",
        "previsao_saida": "---",
        "prestador": "MATEUS APARECIDO DE LIMA SANTOS",
        "servico": "Trocar retentor do rotor L/E - (Fazenda São Pedro)",
        "liberado_por": "Mauricio"
    },
    {
        "solicitante": "NATALINO ANTONIO JUSTINO",
        "frota": "5035",
        "modelo": "ATOMIZADOR FMC 4000 LT",
        "os": "113271",
        "data_entrada": "26/06/2025",
        "previsao_saida": "---",
        "prestador": "MATEUS APARECIDO DE LIMA SANTOS",
        "servico": "Revisar equipamento, bomba e conexões - (Fazenda Alvorada)",
        "liberado_por": "Mauricio"
    },
    {
        "solicitante": "ROMES ROSA SILVA",
        "frota": "5060",
        "modelo": "PULVERIZADOR 2000 LT FMC",
        "os": "113153",
        "data_entrada": "25/06/2025",
        "previsao_saida": "---",
        "prestador": "JOSE RENATO LEMES MARINHO 06173795990",
        "servico": "Fazer reforço no suporte dos braços - (Fazenda São Pedro)",
        "liberado_por": "Mauricio"
    },
    {
        "solicitante": "LEOJABES GUIMARAES SOUZA NASCIMENTO",
        "frota": "5804",
        "modelo": "PULVERIZADOR FMC 4000 BILATERA",
        "os": "113131",
        "data_entrada": "25/06/2025",
        "previsao_saida": "---",
        "prestador": "JOSE RENATO LEMES MARINHO 06173795990",
        "servico": "Readequar as proteções dos bicos do sistema de pulverização eletrostática (SPE), que estão colidindo com galhos e sofrendo quebras durante a operação - (Fazenda São Paulo)",
        "liberado_por": "Mauricio"
    },
    {
        "solicitante": "MURILO J ONCK LEMES DA SILVA",
        "frota": "5336",
        "modelo": "PULVERIZADOR 2000 LT FMC",
        "os": "113088",
        "data_entrada": "24/06/2025",
        "previsao_saida": "---",
        "prestador": "nan",
        "servico": "Fazer fibra em trinca no tanque - (Fazenda Bela Manhã)",
        "liberado_por": "Mauricio"
    },
    {
        "solicitante": "ADRIANO CLAUDIO FIRMINO",
        "frota": "5005",
        "modelo": "PULVERIZADOR 2000 LT MARTHGNIA",
        "os": "113081",
        "data_entrada": "24/06/2025",
        "previsao_saida": "---",
        "prestador": "JOSE RENATO LEMES MARINHO 06173795990",
        "servico": "Quebra do cabeçalho do tanque - (Fazenda Nova Manhã)",
        "liberado_por": "Mauricio"
    },
    {
        "solicitante": "ANTONIO PAULO LARENTIS ALVES",
        "frota": "5401",
        "modelo": "ATOMIZADOR JACTO 4000 LT",
        "os": "113066",
        "data_entrada": "24/06/2025",
        "previsao_saida": "---",
        "prestador": "JOSE RENATO LEMES MARINHO 06173795990",
        "servico": "Realinhas estrutura do braço, amassado após colisão - (Fazenda São Pedro)",
        "liberado_por": "Mauricio"
    },
    {
        "solicitante": "ALTIERES SOARES FERREIRA",
        "frota": "5479",
        "modelo": "PULVERIZADOR 600 LT JACTO",
        "os": "113059",
        "data_entrada": "24/06/2025",
        "previsao_saida": "---",
        "prestador": "MATEUS APARECIDO DE LIMA SANTOS",
        "servico": "Revisar bomba, misturando água no óleo - (Fazenda Pedra Verde)",
        "liberado_por": "Mauricio"
    },
    {
        "solicitante": "ALTIERES SOARES FERREIRA",
        "frota": "5479",
        "modelo": "PULVERIZADOR 600 LT JACTO",
        "os": "113058",
        "data_entrada": "24/06/2025",
        "previsao_saida": "---",
        "prestador": "MICHEL LEANDRO DA SILVA 02465062964",
        "servico": "Fazer serviço de fibra no tanque - (Fazenda Pedra Verde)",
        "liberado_por": "Mauricio"
    },
    {
        "solicitante": "ROMES ROSA SILVA",
        "frota": "5615",
        "modelo": "PULVERIZADOR 2000 LT JACTO",
        "os": "112978",
        "data_entrada": "23/06/2025",
        "previsao_saida": "---",
        "prestador": "MATEUS APARECIDO DE LIMA SANTOS",
        "servico": "Vazamento de óleo na bomba - (Fazenda São Pedro)",
        "liberado_por": "Mauricio"
    },
    {
        "solicitante": "ADRIANO CLAUDIO FIRMINO",
        "frota": "5191",
        "modelo": "ATOMIZADOR FMC COPLING 4000 LT",
        "os": "112759",
        "data_entrada": "18/06/2025",
        "previsao_saida": "---",
        "prestador": "JOSE RENATO LEMES MARINHO 06173795990",
        "servico": "Fazer proteção de partes móveis (Correia da turbina) e instalar escada na torra  (Avaliar necessidade) - (Fazenda Nova Manhã)",
        "liberado_por": "Mauricio"
    },
    {
        "solicitante": "JOAO VITOR DUBAY DA SILVA",
        "frota": "5490",
        "modelo": "PLANTADEIRA SH13D",
        "os": "112721",
        "data_entrada": "18/06/2025",
        "previsao_saida": "---",
        "prestador": "nan",
        "servico": "Verificada ausência de 6 bicas de distribuição de sementes e de 1 conjunto de disco dosador - (Fazenda Bela Manhã)",
        "liberado_por": "Mauricio"
    },
    {
        "solicitante": "DIEGO GOMES CAMBOI",
        "frota": "5290",
        "modelo": "PULVERIZADOR 4000 LT - NATALI",
        "os": "112629",
        "data_entrada": "16/06/2025",
        "previsao_saida": "---",
        "prestador": "JOSE RENATO LEMES MARINHO 06173795990",
        "servico": "Refazer rosca para colocar bico graxeiro - (Fazenda Santa Izabel)",
        "liberado_por": "Mauricio"
    },
    {
        "solicitante": "DANILO MULARI GONZAGA",
        "frota": "5524",
        "modelo": "DISTRIBUIDOR FARTUS 8.0 GRANEL",
        "os": "112593",
        "data_entrada": "16/06/2025",
        "previsao_saida": "---",
        "prestador": "JOSE RENATO LEMES MARINHO 06173795990",
        "servico": "Substituir chapas dos pratos/discos do sistema distribuidor, devido a desgaste - (Fazenda Estrela)",
        "liberado_por": "Mauricio"
    },
    {
        "solicitante": "JOAO VITOR DUBAY DA SILVA",
        "frota": "5110",
        "modelo": "SUBSOLADOR STARA",
        "os": "112539",
        "data_entrada": "13/06/2025",
        "previsao_saida": "---",
        "prestador": "JOSE RENATO LEMES MARINHO 06173795990",
        "servico": "Verificar rodas com \"jogo\" - (Fazenda Estrela VI)",
        "liberado_por": "Mauricio"
    },
    {
        "solicitante": "RENNAN ARCANJO CREPALDI",
        "frota": "5673",
        "modelo": "PULV.BARRA SUBCOPA DUPLA FRON",
        "os": "112409",
        "data_entrada": "12/06/2025",
        "previsao_saida": "---",
        "prestador": "JOSE RENATO LEMES MARINHO 06173795990",
        "servico": "Realinhar barrinha - (Fazenda NSA)",
        "liberado_por": "Mauricio"
    },
    {
        "solicitante": "ROMES ROSA SILVA",
        "frota": "5611",
        "modelo": "TRINCHA LEVE ARTI. TRLA 180H",
        "os": "112366",
        "data_entrada": "12/06/2025",
        "previsao_saida": "---",
        "prestador": "MATEUS APARECIDO DE LIMA SANTOS",
        "servico": "Fazer solda nas proteções anti-arremesso e trocar jogo de martelos - (Fazenda São Pedro)",
        "liberado_por": "Mauricio"
    },
    {
        "solicitante": "MARCIO JUNIO NUNES DE OLIVEIRA",
        "frota": "5175",
        "modelo": "TANQUE DE AGUA 4000 LT",
        "os": "112275",
        "data_entrada": "10/06/2025",
        "previsao_saida": "---",
        "prestador": "JOSE RENATO LEMES MARINHO 06173795990",
        "servico": "Reformar estrutura superior do tanque (Fazenda São Severino)",
        "liberado_por": "Mauricio"
    },
    {
        "solicitante": "ROMES ROSA SILVA",
        "frota": "5715",
        "modelo": "TANQUE DE AGUA 6500",
        "os": "112208",
        "data_entrada": "09/06/2025",
        "previsao_saida": "---",
        "prestador": "RIVELINO LONGATO 03100998979",
        "servico": "Executar reforço estrutural no cabeçalho do tanque, visando aumentar a resistência mecânica e prevenir trincas ou deformações decorrentes de esforços operacionais, trocar mangueira e registro - (Fazenda São Pedro)",
        "liberado_por": "Mauricio"
    },
    {
        "solicitante": "ADRIANO CLAUDIO FIRMINO",
        "frota": "5128",
        "modelo": "ATOMIZADOR FMC COPLING 4000 LT",
        "os": "111561",
        "data_entrada": "30/05/2025",
        "previsao_saida": "---",
        "prestador": "JORGINHO IMPLEMENTO E TRATORES AGRICOLA",
        "servico": "Rolamento do eixo dianteiro que liga na bomba estourado - (Fazenda Nova Manhã)",
        "liberado_por": "Mauricio"
    },
    {
        "solicitante": "ROMES ROSA SILVA",
        "frota": "5171",
        "modelo": "PULVERIZADOR 2000 LT JACTO",
        "os": "111430",
        "data_entrada": "27/05/2025",
        "previsao_saida": "---",
        "prestador": "GILSON CESAR ALVES DOS SANTOS 660964809",
        "servico": "Soldar suporte para transportar cone - (Fazenda São Pedro)",
        "liberado_por": "Mauricio"
    },
    {
        "solicitante": "MURILO J ONCK LEMES DA SILVA",
        "frota": "5078",
        "modelo": "RC2 E 2600 LSL TATU",
        "os": "110736",
        "data_entrada": "16/05/2025",
        "previsao_saida": "---",
        "prestador": "JOSE RENATO LEMES MARINHO 06173795990",
        "servico": "Colocar proteção anti-arremesso e fazer solda em trinca - (Fazenda Bela Manhã)",
        "liberado_por": "Mauricio"
    },
    {
        "solicitante": "DIEGO GOMES CAMBOI",
        "frota": "5210",
        "modelo": "PULVERIZADOR 4000 LT - NATALI",
        "os": "110604",
        "data_entrada": "15/05/2025",
        "previsao_saida": "---",
        "prestador": "nan",
        "servico": "Fazer alongador do ramal - (Fazenda Santa Izabel)",
        "liberado_por": "Mauricio"
    },
    {
        "solicitante": "ADRIANO CLAUDIO FIRMINO",
        "frota": "5129",
        "modelo": "ATOMIZADOR FMC COPLING 4000 LT",
        "os": "110312",
        "data_entrada": "09/05/2025",
        "previsao_saida": "---",
        "prestador": "nan",
        "servico": "Vazamento no pistão - (Fazenda Nova Manhã)",
        "liberado_por": "Mauricio"
    },
    {
        "solicitante": "ROMES ROSA SILVA",
        "frota": "5188",
        "modelo": "PULVERIZADOR 600 LT MONTANA",
        "os": "109725",
        "data_entrada": "30/04/2025",
        "previsao_saida": "---",
        "prestador": "JORGINHO IMPLEMENTO E TRATORES AGRICOLA",
        "servico": "Substituir polia do agitador da turbina-hélice, que se encontra quebrada, comprometendo o funcionamento do sistema de agitação da calda. Verificar o estado geral do mecanismo e demais componentes associados - (Fazenda São Pedro)",
        "liberado_por": "Mauricio"
    }
]