[
  {
    "solicitado": "ANTONIO PAULO LARENTIS ALVES",
    "frota": "46",
    "os": "110663",
    "data": "16/05/2025",
    "prestador": "Prestador não definido",
    "servico": "Vazamento na mangueira de diesel e entrada de ar no sistema de combustível - (Fazenda Minuano)"
  },
  {
    "frota": "5366",
    "os": "110601",
    "data": "15/05/2025",
    "prestador": "IAGO MANUNTENCAO AGRICOLA LTDA",
    "servico": "Folga no eixo da roda L/D - (Fazenda Minuano)"
  },
  {
    "frota": "46",
    "os": "110544",
    "data": "14/05/2025",
    "prestador": "PEDRO PEREIRA MONTESSANI EIRELI - ME",
    "servico": "Trator não marca temperatura no painel - (Fazenda Minuano)"
  },
  {
    "frota": "26",
    "os": "110503",
    "data": "14/05/2025",
    "prestador": "CICERO MUNIZ DA SILVA",
    "servico": "Verificar alavanca de cambio \"bobo\" - (Fazenda Minuano)"
  },
  {
    "frota": "5767",
    "os": "110438",
    "data": "13/05/2025",
    "prestador": "MURILO SILVA 09207298945",
    "servico": "Verificar fio do SPE quebrado - (Fazenda Minuano)"
  },
  {
    "frota": "253",
    "os": "110380",
    "data": "12/05/2025",
    "prestador": "JOCAR LTDA",
    "servico": "Revisar ar-condicionado"
  },
  {
    "frota": "118",
    "os": "110366",
    "data": "12/05/2025",
    "prestador": "JOSE RENATO LEMES MARINHO 06173795990",
    "servico": "Fazer solda na escada quebrada - (Fazenda Minuano)"
  },
  {
    "frota": "155",
    "os": "110309",
    "data": "09/05/2025",
    "prestador": "RIVELINO LONGATO 03100998979",
    "servico": "Pneu dianteiro L/D furado - (Fazenda Minuano)"
  },
  {
    "frota": "144",
    "os": "110047",
    "data": "06/05/2025",
    "prestador": "PEDRO PEREIRA MONTESSANI EIRELI - ME",
    "servico": "Instalar lanternas do alerta quebrada - (Fazenda Minuano)"
  },
  {
    "frota": "253",
    "os": "109723",
    "data": "30/04/2025",
    "prestador": "ANDERSON DIEGO BICUDO 08122062903",
    "servico": "Avaliar ruído anormal na TDP - (Fazenda Minuano)"
  },
  {
    "frota": "5631",
    "os": "106948",
    "data": "12/03/2025",
    "prestador": "Prestador não definido",
    "servico": "Instalar correntes de proteção - (Fazenda Minuano)"
  },
  {
    "frota": "5500",
    "os": "104756",
    "data": "03/02/2025",
    "prestador": "JOSE RENATO LEMES MARINHO 06173795990",
    "servico": "Fazer proteção e desamassar suporte do esqui - (Fazenda Minuano)"
  }
]