[
  {
    "frota": "149",
    "os": "116855",
    "data": "19/08/2025",
    "prestador": "RIVELINO LONGATO 03100998979",
    "servico": "Pneu traseiro L/D furado - (Fazenda Estrela)"
  },
  {
    "frota": "110",
    "os": "116575",
    "data": "13/08/2025",
    "prestador": "PEDRO PEREIRA MONTESSANI EIRELI - ME",
    "servico": "Relógio horimetro  não funciona e luz do alternador acessa no painel  - (Fazenda Estrela)"
  },
  {
    "frota": "289",
    "os": "114527",
    "data": "16/07/2025",
    "prestador": "ANDERSON DIEGO BICUDO 08122062903",
    "servico": "Avaliar vazamento de óleo na parte frontal do trator - (Fazenda Estrela)"
  }
]