[
  {
    "frota": "5484",
    "os": "115342",
    "data": "25/07/2025",
    "prestador": "INJECOES DIESEL NOROESTE LTDA.",
    "servico": "Equipamento não dá partida. Durante a verificação, foi identificado filtro de diesel sujo - (Fazenda Minuano)"
  },
  {
    "frota": "253",
    "os": "115306",
    "data": "25/07/2025",
    "prestador": "RIVELINO LONGATO 03100998979",
    "servico": "Pneu traseiro L/D furado - (Fazenda Minuano)"
  },
  {
    "frota": "253",
    "os": "115305",
    "data": "25/07/2025",
    "prestador": "nan",
    "servico": "Cano de óleo do motor furada - (Fazenda Minuano)"
  },
  {
    "frota": "24",
    "os": "115192",
    "data": "24/07/2025",
    "prestador": "INJECOES DIESEL NOROESTE LTDA.",
    "servico": "Cano de diesel furado - (Fazenda Minuano)"
  },
  {
    "frota": "80",
    "os": "115150",
    "data": "23/07/2025",
    "prestador": "nan",
    "servico": "Vazamento de óleo no pistão da concha do trator  - (Fazenda São Severino)"
  },
  {
    "frota": "144",
    "os": "114876",
    "data": "21/07/2025",
    "prestador": "CICERO MUNIZ DA SILVA",
    "servico": "Quebra do cabo do acelerador de mão - (Fazenda Minuano)"
  },
  {
    "frota": "255",
    "os": "113164",
    "data": "14/07/2025",
    "prestador": "ANDERSON DIEGO BICUDO 08122062903",
    "servico": "Vazamento no burrinho do freio, vazamento no cilindro de freio.  - (Fazenda Minuano)"
  },
  {
    "frota": "155",
    "os": "114194",
    "data": "14/07/2025",
    "prestador": "RIVELINO LONGATO 03100998979",
    "servico": "Trocar os pneus dianteiro - Faz Minuano"
  },
  {
    "frota": "5405",
    "os": "113626",
    "data": "23/06/2025",
    "prestador": "M G VEDACOES E PECAS LTDA",
    "servico": "Modificar roçadeira do sistema convencional para ecológica, corrigir folgas no embuchamento das rodas guia traseira, acertar engate do cabeçalho danificado e corrigir trincas na estrutura."
  }
]