[
  {
    "frota": "258",
    "os": "112919",
    "data": "20/06/2025",
    "prestador": "nan",
    "servico": "Vazamento de óleo diesel na bomba - (Fazenda Estrela)"
  },
  {
    "frota": "288",
    "os": "112910",
    "data": "20/06/2025",
    "prestador": "JOCAR LTDA",
    "servico": "Verificar condensador vazando - Faz Estrela"
  },
  {
    "frota": "269",
    "os": "112908",
    "data": "20/06/2025",
    "prestador": "INJECOES DIESEL NOROESTE LTDA.",
    "servico": "Remover vazamento na bomba de combustivel - Faz Estrela"
  },
  {
    "frota": "258",
    "os": "112906",
    "data": "20/06/2025",
    "prestador": "nan",
    "servico": "Soldar escada - Faz Estrela"
  },
  {
    "frota": "5747",
    "os": "112867",
    "data": "19/06/2025",
    "prestador": "RIVELINO LONGATO 03100998979",
    "servico": "Pneu L/E furado - (Fazenda Estrela)"
  }
]