[
  {
    "solicitado": "EDER JOSE FERNANDES DE ALMEIDA",
    "frota": "5424",
    "os": "112107",
    "data": "06/06/2025",
    "prestador": "Prestador não definido",
    "servico": "Vazamento no pistão e niple do comando - (Fazenda Terra Branca)"
  },
  {
    "frota": "5139",
    "os": "112058",
    "data": "05/06/2025",
    "prestador": "Prestador não definido",
    "servico": "Fazer solda em trinca na estrutura do chassi - (Fazenda Terra Branca)"
  },
  {
    "frota": "5495",
    "os": "111593",
    "data": "30/05/2025",
    "prestador": "JOSE RENATO LEMES MARINHO 06173795990",
    "servico": "Substituição das aletas dos pratos do distribuidor de adubo devido a corrosão e soldar proteção de partes móveis (correias traseiras) - (Fazenda Terra Branca)"
  },
  {
    "frota": "5398",
    "os": "111546",
    "data": "29/05/2025",
    "prestador": "IAGO MANUNTENCAO AGRICOLA LTDA",
    "servico": "Verificar agitador de calda com folga no mancal - (Fazenda Terra Branca)"
  },
  {
    "frota": "99",
    "os": "111476",
    "data": "28/05/2025",
    "prestador": "JOSE RENATO LEMES MARINHO 06173795990",
    "servico": "Trocar confeccionar e trocar teto"
  },
  {
    "frota": "5227",
    "os": "111235",
    "data": "23/05/2025",
    "prestador": "IAGO MANUNTENCAO AGRICOLA LTDA",
    "servico": "Vazamento do eixo que desce para os fações - (Fazenda Terra Branca)"
  }
]