[
  {
    "frota": "215",
    "os": "118076",
    "data": "10/09/2025",
    "prestador": "nan",
    "servico": "Troca do engate rápido (Fazenda N. S. A.)"
  },
  {
    "frota": "5629",
    "os": "118057",
    "data": "10/09/2025",
    "prestador": "nan",
    "servico": "Soldar roda guia (Fazenda N. S. A.)"
  },
  {
    "frota": "150",
    "os": "118022",
    "data": "10/09/2025",
    "prestador": "nan",
    "servico": "Fazer regulagem de válvulas e tirar vazamento de óleo de motor - (Fazenda NSA)"
  },
  {
    "frota": "120",
    "os": "117791",
    "data": "04/09/2025",
    "prestador": "nan",
    "servico": "Trocar dos faróis, troca dos reparos do pistão - (Fazenda  Casa Branca)"
  },
  {
    "frota": "5487",
    "os": "117288",
    "data": "27/08/2025",
    "prestador": "nan",
    "servico": "Trocar flange - (Fazenda Casa Branca)"
  }
]