[
  {
    "frota": "109",
    "os": "116617",
    "data": "14/08/2025",
    "prestador": "CICERO MUNIZ DA SILVA",
    "servico": "Avaliar trator com a direção dura - (Pecuária)"
  },
  {
    "frota": "5545",
    "os": "116609",
    "data": "14/08/2025",
    "prestador": "MATEUS APARECIDO DE LIMA SANTOS",
    "servico": "Fazer revisão básica: conferir bomba de pulverização, avaliar mangueiras, conexões e correntes, verificar vazamentos em geral."
  },
  {
    "frota": "5168",
    "os": "115503",
    "data": "29/07/2025",
    "prestador": "JHONY ANDERSON DE CASTRO LAFAYETE 02369",
    "servico": "Fazer bucha do engate da carreta. (Pecuária)"
  },
  {
    "frota": "5067",
    "os": "113933",
    "data": "08/07/2025",
    "prestador": "M G VEDACOES E PECAS LTDA",
    "servico": "Mancal trincado (Pecuária)"
  }
]