[
  {
    "frota": "109",
    "os": "113470",
    "data": "30/06/2025",
    "prestador": "nan",
    "servico": "Avaliar trator com perda de potência em funcionamento. - (Pecuária)"
  },
  {
    "frota": "68",
    "os": "113298",
    "data": "26/06/2025",
    "prestador": "JOSE RENATO LEMES MARINHO 06173795990",
    "servico": "Quebra dos pinos do rabicho - (Pecuaria)"
  },
  {
    "frota": "68",
    "os": "113297",
    "data": "26/06/2025",
    "prestador": "PEDRO PEREIRA MONTESSANI EIRELI - ME",
    "servico": "Suporte do cibié quebrado - (Pecuaria)"
  },
  {
    "frota": "5352",
    "os": "113269",
    "data": "26/06/2025",
    "prestador": "JOSE RENATO LEMES MARINHO 06173795990",
    "servico": "Quebra do parafusos que segura o açoalho e parafusos do suporte da bica - (Pecuaria)"
  },
  {
    "frota": "5351",
    "os": "106930",
    "data": "12/03/2025",
    "prestador": "nan",
    "servico": "Revisão completa -"
  }
]