[
  {
    "frota": "5667",
    "os": "117634",
    "data": "02/09/2025",
    "prestador": "11.268.880 ROSALINA QUINTINO SUETT",
    "servico": "Afiar 4 discos - (Fazenda Casa Branca)"
  },
  {
    "frota": "5778",
    "os": "117602",
    "data": "01/09/2025",
    "prestador": "nan",
    "servico": "Fazer soldas em trincas na estrutura - (Fazenda Casa Branca)"
  },
  {
    "frota": "5348",
    "os": "117580",
    "data": "01/09/2025",
    "prestador": "IAGO MANUNTENCAO AGRICOLA LTDA",
    "servico": "Alterar engrenagens do sistema de transmissão da adubadeira, adequando para aplicação de calcário - (Fazenda Casa Branca)"
  },
  {
    "frota": "5197",
    "os": "117438",
    "data": "28/08/2025",
    "prestador": "JOSE RENATO LEMES MARINHO 06173795990",
    "servico": "Fazer solda em trinca na estrutura - (Fazenda Casa Branca)"
  },
  {
    "frota": "91",
    "os": "117412",
    "data": "28/08/2025",
    "prestador": "ANDERSON DIEGO BICUDO 08122062903",
    "servico": "Vazamento de óleo na junta do cárter - (Fazenda Casa Branca)"
  },
  {
    "frota": "5205",
    "os": "117411",
    "data": "28/08/2025",
    "prestador": "M G VEDACOES E PECAS LTDA",
    "servico": "Vazamento de óleo no retentor do rotor - (Fazenda Casa Branca)_"
  },
  {
    "frota": "265",
    "os": "117275",
    "data": "26/08/2025",
    "prestador": "JOSE RENATO LEMES MARINHO 06173795990",
    "servico": "Degrau da escada do trator quebrada - (Fazenda Casa Branca)"
  },
  {
    "frota": "258",
    "os": "117245",
    "data": "26/08/2025",
    "prestador": "nan",
    "servico": "Verificar vazamento na tampa do hidraulico - Faz Casa Branca"
  },
  {
    "frota": "211",
    "os": "117220",
    "data": "25/08/2025",
    "prestador": "ANDERSON DIEGO BICUDO 08122062903",
    "servico": "Avaliar sistema de embreagem do trator, apresentando dificuldade de acionamento e possível desgaste de componentes. - (Fazenda Casa Branca)"
  },
  {
    "frota": "125",
    "os": "117034",
    "data": "21/08/2025",
    "prestador": "FERNANDA BARBOSA MORANGUEIRA 00413385965",
    "servico": "Trocar banco danificado e trocar borrachas da porta danificadas - (Fazenda Casa Branca)"
  },
  {
    "frota": "165",
    "os": "116596",
    "data": "14/08/2025",
    "prestador": "JOSE RENATO LEMES MARINHO 06173795990",
    "servico": "Fabricar proteção das lanternas traseiras - (Fazenda Casa Branca)"
  },
  {
    "frota": "10217",
    "os": "114790",
    "data": "19/07/2025",
    "prestador": "MICHEL LEANDRO DA SILVA 02465062964",
    "servico": "Verificar dano causado pelo escapamento que encostou no teto do trator e derreteu a estrutura. - (Fazenda Casa Branca)"
  },
  {
    "frota": "265",
    "os": "113516",
    "data": "30/06/2025",
    "prestador": "PEDRO PEREIRA MONTESSANI EIRELI - ME",
    "servico": "Instalar proteção das lanternas L/?? - (Fazenda Casa Branca)"
  }
]