[
  {
    "solicitado": "MURILO J ONCK LEMES DA SILVA",
    "frota": "5078",
    "os": "110736",
    "data": "16/05/2025",
    "prestador": "JOSE RENATO LEMES MARINHO 06173795990",
    "servico": "Colocar proteção anti-arremesso e fazer solda em trinca - (Fazenda Bela Manhã)"
  },
  {
    "frota": "5264",
    "os": "110661",
    "data": "16/05/2025",
    "prestador": "GILSON CESAR ALVES DOS SANTOS 660964809",
    "servico": "Fazer solda no suporte do corote e verificar mola da barra - (Fazenda Bela Manhã)"
  },
  {
    "frota": "10224",
    "os": "110659",
    "data": "16/05/2025",
    "prestador": "PEDRO PEREIRA MONTESSANI EIRELI - ME",
    "servico": "Verificar trator sem partida - (Fazenda Bela Manhã)"
  }
]