[
  {
    "solicitado": "PAULO VINICIUS DOS ANJOS DA CRUZ",
    "frota": "136",
    "os": "111971",
    "data": "03/06/2025",
    "prestador": "PEDRO PEREIRA MONTESSANI EIRELI - ME",
    "servico": "Cibié traseiro e dianteiro queimado - (Fazenda Estrela)"
  },
  {
    "frota": "258",
    "os": "111918",
    "data": "03/06/2025",
    "prestador": "Prestador não definido",
    "servico": "Reajustar escapamento pegando no para-brisa - (Fazenda Estrela)"
  },
  {
    "frota": "258",
    "os": "111917",
    "data": "03/06/2025",
    "prestador": "ANDERSON DIEGO BICUDO 08122062903",
    "servico": "Verificar embreagem não da mais regulagem, e grupo de marcha A,B e C escapando - (Fazenda Estrela)"
  },
  {
    "frota": "268",
    "os": "111648",
    "data": "02/06/2025",
    "prestador": "PEDRO PEREIRA MONTESSANI EIRELI - ME",
    "servico": "Lâmpada do cibié traseiro queimada - (Fazenda Estrela)"
  },
  {
    "frota": "268",
    "os": "111342",
    "data": "27/05/2025",
    "prestador": "PEDRO PEREIRA MONTESSANI EIRELI - ME",
    "servico": "Trocar lanterna dianteira quebrada - (Fazenda Estrela)"
  },
  {
    "frota": "221",
    "os": "111341",
    "data": "27/05/2025",
    "prestador": "PEDRO PEREIRA MONTESSANI EIRELI - ME",
    "servico": "Chicote do cibié quebrado - (Fazenda Estrela)"
  },
  {
    "frota": "189",
    "os": "110510",
    "data": "14/05/2025",
    "prestador": "JOSE RENATO LEMES MARINHO 06173795990",
    "servico": "Confeccionar e instalar proteções das lanternas do paralamas"
  },
  {
    "frota": "5491",
    "os": "109153",
    "data": "22/04/2025",
    "prestador": "FM MANUTENÇÃO",
    "servico": "Adaptar ramal para adequar quantidade de bico - (Fazenda Estrela)"
  }
]