[
  {
    "frota": "215",
    "os": "113811",
    "data": "04/07/2025",
    "prestador": "JOCAR LTDA",
    "servico": "Verificar A/C não gela - (Fazenda NSA)"
  },
  {
    "frota": "5758",
    "os": "113702",
    "data": "03/07/2025",
    "prestador": "M G VEDACOES E PECAS LTDA",
    "servico": "Fazer solda tanque de diesel, furado na parte inferior traseira e na frente"
  },
  {
    "frota": "5229",
    "os": "113679",
    "data": "02/07/2025",
    "prestador": "M G VEDACOES E PECAS LTDA",
    "servico": "Verificar barra de corte danificada - (Fazenda NSA)"
  },
  {
    "frota": "5502",
    "os": "113644",
    "data": "02/07/2025",
    "prestador": "nan",
    "servico": "Troca de terminal danificado - (Fazenda NSA)"
  },
  {
    "frota": "5418",
    "os": "113643",
    "data": "02/07/2025",
    "prestador": "JOSE RENATO LEMES MARINHO 06173795990",
    "servico": "Reconstruir a caixa de transporte de produtos fixada na traseira do tanque - (Fazenda NSA)"
  },
  {
    "frota": "5778",
    "os": "113581",
    "data": "01/07/2025",
    "prestador": "GRANEL IMPLEMENTOS AGRICOLA LTDA",
    "servico": "Verificar quebra da esteira da adubadeira, comprometendo o transporte e a distribuição do insumo. - (Fazenda NSA)"
  },
  {
    "frota": "5758",
    "os": "113510",
    "data": "30/06/2025",
    "prestador": "JOSE RENATO LEMES MARINHO 06173795990",
    "servico": "Fazer solda em tanque de diesel furado - (Fazenda NSA)"
  },
  {
    "frota": "5492",
    "os": "112722",
    "data": "16/06/2025",
    "prestador": "JORGINHO IMPLEMENTO E TRATORES AGRICOLA",
    "servico": "- Recuperar fibra do tanque aonde vai a cinta para fixar; Refazer sistema abre e fecha das abas da torre L/D e L/E."
  },
  {
    "frota": "5673",
    "os": "112409",
    "data": "12/06/2025",
    "prestador": "JOSE RENATO LEMES MARINHO 06173795990",
    "servico": "Realinhar barrinha - (Fazenda NSA)"
  },
  {
    "frota": "5058",
    "os": "112282",
    "data": "10/06/2025",
    "prestador": "nan",
    "servico": "Revisão geral - (Fazenda NSA) - Recolher para Oficina"
  }
]