[
  {
    "frota": "5603",
    "cd_equipamento": "5603",
    "modelo": "ATOMIZADOR FMC COPLING 4000 LT",
    "os": "111255",
    "data_entrada": "23/05/2025",
    "servico": "Fazer fibra em trincas na torre - (Fazenda Bela Manhã)\nLiberado Sr. Mauricio"
  },
  {
    "frota": "5597",
    "cd_equipamento": "5597",
    "modelo": "PULVERIZADOR 2000 LT FMC",
    "os": "111254",
    "data_entrada": "23/05/2025",
    "servico": "Trinca na fibra do tanque e verificar rosca da boca do tanque - (Fazenda Bela Manhã)\nLiberado Sr. Mauricio"
  },
  {
    "frota": "5061",
    "cd_equipamento": "5061",
    "modelo": "ATOMIZADOR FMC 4000 LT",
    "os": "110953",
    "data_entrada": "20/05/2025",
    "servico": "Fazer fibra na torre e trocar barra roscada - (Fazenda Estrela)\nLiberado Sr. Mauricio"
  }
]