[
  {
    "frota": "5529",
    "cd_equipamento": "5529",
    "modelo": "PUL.TURBO 4000 NATALI ALFA",
    "os": "117607",
    "data_entrada": "01/09/2025",
    "servico": "Tampar buracos do ramal velho na fibra nos dois lados da torre.\nFazenda Nova Manhã\nResponsável Sr. Maurício"
  },
  {
    "frota": "253",
    "cd_equipamento": "253",
    "modelo": "TRATOR JOHN DEERE 5080E",
    "os": "117595",
    "data_entrada": "01/09/2025",
    "servico": "Concerto e pintura dos para-lamas (Minuano/Oficina Cocamar)\nResponsavel Sr. Carlos Aparecido"
  }
]