[
  {
    "frota": "325",
    "cd_equipamento": "325",
    "modelo": "TRATOR NEW HOLANDTL5.80",
    "os": "117152",
    "data_entrada": "26/08/2025",
    "servico": "Revisão 900hrs - (Fazenda Estrela)\nLiberado Sr. Wilson"
  },
  {
    "frota": "333",
    "cd_equipamento": "333",
    "modelo": "TRATOR NEW HOLANDTL5.80",
    "os": "117154",
    "data_entrada": "26/08/2025",
    "servico": "Revisão de 300hrs - (Faz. São José)\nLiberado Sr. Wilson"
  },
  {
    "frota": "314",
    "cd_equipamento": "314",
    "modelo": "TRATOR NEW HOLANDTL5.80",
    "os": "116893",
    "data_entrada": "19/08/2025",
    "servico": "Revisão de 1200 hrs - (Fazenda Nova Manhã)\nSolicitado Sr. Elismar\nResponsavel Sr. Wilson"
  }
]