[
  {
    "frota": "220",
    "cd_equipamento": "220",
    "modelo": "TRATOR JOHN DEERE 5080E",
    "os": "114161",
    "data_entrada": "11/07/2025",
    "servico": "Revisar bomba e bico - Faz Terra Branca\nAutorizado Arthur"
  },
  {
    "frota": "159",
    "cd_equipamento": "159",
    "modelo": "TRATOR JOHN DEERE 5055E",
    "os": "114137",
    "data_entrada": "11/07/2025",
    "servico": "Verificar vazamento de óleo na bomba injetora - (Fazenda São Pedro)\nSolicitado Sr. Romes\nResponsavel Sr. Arthur"
  },
  {
    "frota": "156",
    "cd_equipamento": "156",
    "modelo": "TRATOR JOHN DEERE 5055E",
    "os": "114113",
    "data_entrada": "10/07/2025",
    "servico": "Vazamento na bomba injetora (Fazenda São Pedro)\nSolicitante Sr. Romes\nResponsável Sr. Arthur"
  },
  {
    "frota": "143",
    "cd_equipamento": "143",
    "modelo": "TRATOR MASSEY FERGUSON 4275 4R",
    "os": "113824",
    "data_entrada": "05/07/2025",
    "servico": "Verificar trator não pega, aparente entrada de ar no sistema e código de erro no painel, bateria está fraca também.\nFazenda Bela Manhã\nSolicitado Sr. Murilo\nResponsável Sr. Arthur"
  }
]