[
  {
    "frota": "215",
    "cd_equipamento": "215",
    "modelo": "TRATOR JOHN DEERE 5070 E",
    "os": "115188",
    "data_entrada": "24/07/2025",
    "servico": "Fazer fibra nos para-lamas - (Fazenda NSA)\nSolicitado Sr. Rennan\nResponsavel Sr. Arthur"
  },
  {
    "frota": "5598",
    "cd_equipamento": "5598",
    "modelo": "ATOMIZADOR FMC COPLING 4000 LT",
    "os": "114865",
    "data_entrada": "21/07/2025",
    "servico": "Fazer fibra na torre - (Fazenda NSA)\nSolicitado Sr. Rennan \nResponsável Sr. Mauricio"
  },
  {
    "frota": "10217",
    "cd_equipamento": "10217",
    "modelo": "TRATOR JOHN DEERE 5080E",
    "os": "114790",
    "data_entrada": "19/07/2025",
    "servico": "Verificar dano causado pelo escapamento que encostou no teto do trator e derreteu a estrutura. - (Fazenda Casa Branca)\nSolicitado Sr. João Paulo\nResponsavel Sr. Arthur"
  },
  {
    "frota": "10220",
    "cd_equipamento": "10220",
    "modelo": "TRATOR JOHN DEERE 5080E",
    "os": "114789",
    "data_entrada": "19/07/2025",
    "servico": "Realizar serviço de fibra na capota do trator, recuperando danos estruturais e garantindo proteção adequada ao operador. - (Fazenda  Casa Branca)\nSolicitado Sr. João Paulo\nResponsavel Sr. Arthur"
  },
  {
    "frota": "5022",
    "cd_equipamento": "5022",
    "modelo": "ATOMIZADOR FMC 4000 LT",
    "os": "114693",
    "data_entrada": "17/07/2025",
    "servico": "Trinca na fibra embaixo da cinta de fixação do tanque - (Fazenda Estrela)\nSolicitado Sr. Carlos (Comboio)\nResponsavel Sr. Mauricio"
  },
  {
    "frota": "5697",
    "cd_equipamento": "5697",
    "modelo": "PULVERIZADOR 2000 LT",
    "os": "114636",
    "data_entrada": "16/07/2025",
    "servico": "Fazer fibra no tanque de drench - (Faz. Bela Manhã)\nSolicitado Sr. Murilo\nLiberado Sr. Mauricio"
  },
  {
    "frota": "504",
    "cd_equipamento": "504",
    "modelo": "ONIBUS",
    "os": "114227",
    "data_entrada": "14/07/2025",
    "servico": "Recuperar lateral do onibus - Oficina\nAutorizado Arthur"
  },
  {
    "frota": "5748",
    "cd_equipamento": "5748",
    "modelo": "PULVERIZADOR FMC 4000 BILATERA",
    "os": "113866",
    "data_entrada": "07/07/2025",
    "servico": "Fazer fibra na base turbina - (Fazenda Estrela)\nSolicitado Sr. Carlos (Comboio)\nResponsavel Sr. Mauricio"
  }
]