[
  {
    "frota": "5735",
    "cd_equipamento": "5735",
    "modelo": "ADUBADORA E SEMEADORA MS100",
    "os": "114173",
    "data_entrada": "11/07/2025",
    "servico": "Verificar funcionamento da maquina de boro - Faz São Severino\nAutorizado Arthur"
  },
  {
    "frota": "156",
    "cd_equipamento": "156",
    "modelo": "TRATOR JOHN DEERE 5055E",
    "os": "114154",
    "data_entrada": "11/07/2025",
    "servico": "Revisão de sistema eletrico da sinalização - (Fazenda São Pedro)\nSolicitado Sr. Romes\nResponsavel Sr. Arthur"
  },
  {
    "frota": "5442",
    "cd_equipamento": "5442",
    "modelo": "CONJUNTO PODADOR WWD",
    "os": "114153",
    "data_entrada": "11/07/2025",
    "servico": "Instalar faróis auxiliares para trabalhar no turno da noite - (Fazenda São Pedro)\nSolicitado Sr. Romes\nResponsavel Sr. Arthur"
  },
  {
    "frota": "230",
    "cd_equipamento": "230",
    "modelo": "TRATOR VALTRA A124L 4X4",
    "os": "114136",
    "data_entrada": "11/07/2025",
    "servico": "Verificar alternador não carrega a bateria - (Fazenda Estrela 6)\nSolicitado Sr. Antônio Vinício\nResponsavel Sr. Arthur"
  },
  {
    "frota": "165",
    "cd_equipamento": "165",
    "modelo": "TRATOR JOHN DEERE 6415 4X4",
    "os": "114132",
    "data_entrada": "11/07/2025",
    "servico": "Revisar sinalização e iluminação, nada funciona. Instalar fiação do limpador de para-brisa - (Fazenda Estrela) \nSolicitado Sr. Paulo Vinicius \nResponsavel Sr. Arthur"
  },
  {
    "frota": "16",
    "cd_equipamento": "16",
    "modelo": "TRATOR MASSEY FERGUSON 275/2",
    "os": "114128",
    "data_entrada": "11/07/2025",
    "servico": "Revisar partida, primeira partida do dia tem não funciona - Viveiro\nAutorizado Arthur"
  },
  {
    "frota": "77",
    "cd_equipamento": "77",
    "modelo": "TRATOR JOHN DEERE 5403 4X4",
    "os": "114126",
    "data_entrada": "11/07/2025",
    "servico": "Equipamento não aciona a partida e não apresenta sinal no painel. Necessário verificar sistema elétrico - (Fazenda Santa Luiza)\nSolicitado Sr. Jonh\nResponsavel Sr. Arthur"
  },
  {
    "frota": "271",
    "cd_equipamento": "271",
    "modelo": "TRATOR JOHN DEERE 5080E",
    "os": "114125",
    "data_entrada": "10/07/2025",
    "servico": "Faróis do teto não funcionam - (Fazenda Santa Luiza)\nSolicitado Sr. Clodoaldo (Agrônomo)\nResponsavel Sr. Arthur"
  },
  {
    "frota": "118",
    "cd_equipamento": "118",
    "modelo": "TRATOR JOHN DEERE 5078 E 4X4",
    "os": "114120",
    "data_entrada": "10/07/2025",
    "servico": "Trocar alternado - Faz Minuano\nAutorizado Arthur"
  },
  {
    "frota": "269",
    "cd_equipamento": "269",
    "modelo": "TRATOR JOHN DEERE 5080E",
    "os": "114055",
    "data_entrada": "10/07/2025",
    "servico": "Verificar faróis piscando (Fazenda Estrela)\nSolicitado Sr. Carlos (Comboio)\nResponsavel Sr. Arthur"
  },
  {
    "frota": "248",
    "cd_equipamento": "248",
    "modelo": "TRATOR JOHN DEERE 5080EN",
    "os": "114054",
    "data_entrada": "10/07/2025",
    "servico": "Verificar fios do cibié traseiro rompido - (Fazenda Estrela)\nSolicitado Sr. Carlos (Comboio)\nResponsavel Sr. Arthur"
  },
  {
    "frota": "211",
    "cd_equipamento": "211",
    "modelo": "TRATOR JOHN DEERE 5070 E",
    "os": "114044",
    "data_entrada": "10/07/2025",
    "servico": "Verificar faróis e pisca alerta não ascende - (Fazenda São Paulo)\nSolicitado Sr. Leojabes\nResponsavel Sr. Arthur"
  },
  {
    "frota": "113",
    "cd_equipamento": "113",
    "modelo": "TRATOR JOHN DEERE 5603 4X4",
    "os": "114029",
    "data_entrada": "09/07/2025",
    "servico": "Verificar alternador, trator sem partida - (Fazenda Pedra Verde)\nSolicitado Sr. Altieres\nResponsavel Sr. Arthur"
  },
  {
    "frota": "5736",
    "cd_equipamento": "5736",
    "modelo": "ADUBADORA E SEMEADORA MS100",
    "os": "114022",
    "data_entrada": "09/07/2025",
    "servico": "Verificar motor eletrico não aciona - (Fazenda Minuano)\nSolicitado Sr. Antônio\nResponsavel Sr. Arthur"
  },
  {
    "frota": "222",
    "cd_equipamento": "222",
    "modelo": "TRATOR JOHN DEERE 5080E",
    "os": "114011",
    "data_entrada": "09/07/2025",
    "servico": "Cibié dianteiro queimado - (Fazenda Estrela)\nSolicitado Sr. Carlos\nResponsavel Sr. Arthur"
  },
  {
    "frota": "132",
    "cd_equipamento": "132",
    "modelo": "TRATOR NEW HOLLAND TL75E",
    "os": "113998",
    "data_entrada": "09/07/2025",
    "servico": "Revisar sistema eletrico - Oficina\nAutorizado Arthur"
  },
  {
    "frota": "98",
    "cd_equipamento": "98",
    "modelo": "TRATOR JOHN DEERE 5065 4X4",
    "os": "113905",
    "data_entrada": "08/07/2025",
    "servico": "Revisar sistema eletrico do trator - Faz Casa Branca\nAutorizado Arthur"
  },
  {
    "frota": "145",
    "cd_equipamento": "145",
    "modelo": "PA CARREGADEIRA 924K",
    "os": "113853",
    "data_entrada": "07/07/2025",
    "servico": "Avaliar  sistema elétrico do abastecimento (pontos positivos e negativos).\nAjustar ponto de entalhado do limpador de para-brisa. - (Oficina)\nSolicitado Sr. Rafael \nResponsavel Sr. Rafael"
  },
  {
    "frota": "5361",
    "cd_equipamento": "5361",
    "modelo": "ADUBADORA E SEMEADORA MS60",
    "os": "113835",
    "data_entrada": "07/07/2025",
    "servico": "Substituir disco espalhador e kit de reparo do eixo - (Fazenda Estrela)\nSolicitado Sr. Danilo  Mulari\nResponsavel Sr. Arthur"
  },
  {
    "frota": "318",
    "cd_equipamento": "318",
    "modelo": "TRATOR NEW HOLANDTL5.80",
    "os": "113696",
    "data_entrada": "03/07/2025",
    "servico": "Verificar falha no funcionamento da buzina - (Fazenda São Severino)\nSolicitado Sr. Cassio\nResponsavel Sr. Arthur"
  },
  {
    "frota": "265",
    "cd_equipamento": "265",
    "modelo": "TRATOR JOHN DEERE 5080E",
    "os": "113516",
    "data_entrada": "30/06/2025",
    "servico": "Instalar proteção das lanternas L/?? - (Fazenda Casa Branca)\nSolicitado Sr. João\nResponsavel Sr. Arthur"
  },
  {
    "frota": "5662",
    "cd_equipamento": "5662",
    "modelo": "ADUBADEIRA FARTUS 5.0 GRANEL",
    "os": "113221",
    "data_entrada": "25/06/2025",
    "servico": "Revisar chicote e conectores elétricos danificados - (Fazenda Terra Branca)\nSolicitado Sr. João Vitor (Subgerente)\nResponsavel Sr. Arthur"
  },
  {
    "frota": "142",
    "cd_equipamento": "142",
    "modelo": "TRATOR MASSEY FERGUSON 4275 4R",
    "os": "113077",
    "data_entrada": "24/06/2025",
    "servico": "Revisar motor de partida, trator sem partida - (Fazenda Nova Manhã)\nSolicitado Sr. Elismar \nResponsavel Sr. Arthur"
  },
  {
    "frota": "332",
    "cd_equipamento": "332",
    "modelo": "TRATOR NEW HOLANDTL5.80",
    "os": "113064",
    "data_entrada": "24/06/2025",
    "servico": "Trocar lanterna traseira quebrada - (Fazenda SP)\nSolicitado Sr. Leojabes\nResponsavel Sr. Arthur"
  },
  {
    "frota": "143",
    "cd_equipamento": "143",
    "modelo": "TRATOR MASSEY FERGUSON 4275 4R",
    "os": "113005",
    "data_entrada": "23/06/2025",
    "servico": "Fazer revisão no sistema eletrico da iluminação - (Fazenda Bela Manhã)\nSolicitado Sr. Murilo\nResponsavel Sr. Arthur"
  },
  {
    "frota": "266",
    "cd_equipamento": "266",
    "modelo": "TRATOR JOHN DEERE 7230J",
    "os": "112033",
    "data_entrada": "04/06/2025",
    "servico": "Verificar alerta não funciona - (Fazenda Estrela VI)\nLiberado Sr. Arthur"
  },
  {
    "frota": "211",
    "cd_equipamento": "211",
    "modelo": "TRATOR JOHN DEERE 5070 E",
    "os": "109027",
    "data_entrada": "17/04/2025",
    "servico": "Instalar lampadas traseiras - (Fazenda SP)\nLiberado Sr. Wilson\nPendencia N° 4243"
  },
  {
    "frota": "127",
    "cd_equipamento": "127",
    "modelo": "GATOR JOHNN DEERE",
    "os": "106664",
    "data_entrada": "06/03/2025",
    "servico": "Revisão elétrica (Oficina)\n(solicitante William)"
  }
]