[
  {
    "frota": "5495",
    "cd_equipamento": "5495",
    "modelo": "ADUBADEIRA DCA2 7500 S-0118",
    "os": "117340",
    "data_entrada": "27/08/2025",
    "servico": "Pneu L/E traseiro furado - (Fazenda Terra Branca)\nSolicitado Sr. Eder\nResponsavel Sr. Mauricio"
  },
  {
    "frota": "165",
    "cd_equipamento": "165",
    "modelo": "TRATOR JOHN DEERE 6415 4X4",
    "os": "117302",
    "data_entrada": "27/08/2025",
    "servico": "Pneu dianteiro L/E - (Fazenda Casa Branca) |Parado|\nSolicitado Sr. João Paulo\nResponsavel Sr. Mauricio"
  },
  {
    "frota": "315",
    "cd_equipamento": "315",
    "modelo": "TRATOR NEW HOLANDTL5.80",
    "os": "117294",
    "data_entrada": "27/08/2025",
    "servico": "Pneu traseiro L/D furado - (Fazenda São Paulo) |Parado|\nSolicitado Sr. Geovane\nResponsavel Sr. Mauricio"
  },
  {
    "frota": "5545",
    "cd_equipamento": "5545",
    "modelo": "PULVERIZADOR BARRA QUADRICICLO",
    "os": "117283",
    "data_entrada": "27/08/2025",
    "servico": "Pneu traseiro L/E traseiro - (Oficina)\nSolicitado Sr. Carlos Aparecido \nResponsavel Sr. Mauricio"
  },
  {
    "frota": "5455",
    "cd_equipamento": "5455",
    "modelo": "CARRETA TRASNP LAR 510/154/030",
    "os": "117243",
    "data_entrada": "26/08/2025",
    "servico": "Sacar e substituir parafusos da roda L/E - (Fazenda Estrela)\nSolicitado Sr. Danilo \nResponsavel Sr. Mauricio"
  },
  {
    "frota": "5487",
    "cd_equipamento": "5487",
    "modelo": "ATOMIZADOR FMC 4000 LT",
    "os": "117128",
    "data_entrada": "26/08/2025",
    "servico": "Trocar pneu traseiro direito estourado \nFazenda Casa Branca\nSolicitado Sr. Paulo Vinicius\nResponsável Sr. Maurício"
  },
  {
    "frota": "5083",
    "cd_equipamento": "5083",
    "modelo": "CARRETA BAG C/ GUINCHO",
    "os": "117195",
    "data_entrada": "25/08/2025",
    "servico": "Pneu L/D furado - (Fazenda SL1) |Parado|\nSolicitado Sr. Izaias\nResponsavel Sr. Mauricio"
  }
]