[
  {
    "frota": "198",
    "cd_equipamento": "198",
    "modelo": "TRATOR JOHN DEERE 5080E",
    "os": "117795",
    "data_entrada": "04/09/2025",
    "servico": "Quebra da alavanca de cambio - (Fazenda Minuano)|Parado|\nSolicitado Sr. Izaias\nResponsvel Sr. Arthur"
  },
  {
    "frota": "216",
    "cd_equipamento": "216",
    "modelo": "TRATOR JOHN DEERE 5070 E",
    "os": "117779",
    "data_entrada": "04/09/2025",
    "servico": "Vazamento no cachimbo do freio - (Fazenda São Paulo)\nSolicitado Sr. Paulo Edson\nResponsavel Sr. Arthur"
  },
  {
    "frota": "103",
    "cd_equipamento": "103",
    "modelo": "TRATOR JOHN DEERE 5065 4X4",
    "os": "117685",
    "data_entrada": "03/09/2025",
    "servico": "Revisar sistema de freio - Faz Minuano\nAutorizado Arthur"
  },
  {
    "frota": "189",
    "cd_equipamento": "189",
    "modelo": "TRATOR NEW HOLAND TL 5.80",
    "os": "117533",
    "data_entrada": "01/09/2025",
    "servico": "Verificar trator com direção dura - (Fazenda NSA)\nSolicitado Sr. Izaias\nResponsavel Sr. Arthur \nP.S Os recente para Solo Verde (116780)"
  },
  {
    "frota": "230",
    "cd_equipamento": "230",
    "modelo": "TRATOR VALTRA A124L 4X4",
    "os": "117381",
    "data_entrada": "28/08/2025",
    "servico": "Regular sistema de freio e substituir coxins da cabine - (Fazenda Úrsula)\nSolicitado Sr. João Vitor Dubay\nResponsavel Sr. Arthur"
  }
]